Workbook

Sheet 正式比赛打法
A1: 正式比赛打法（Decision 1 截止 10/14；D 列是 10/11 实际保存的决策）
A2: 正式比赛从 Start 重新开始，起点和练习轮一样：Cafav 28/145、Cameo 12/120、Crash 70/190，产能 1,000K，2 个研发中心，短贷 $6,660M（7.5%），市值约 $17.6B。标 [推断] 的是从练习轮推出来、还没验证过的做法。
A4: 项目 | B4: Decision 1（Year 1）怎么做 | C4: 依据 | D4: 实际怎么做的（10/11 已保存）
A5: 调研 | B5: 1E、2E、2F、3T、5U 各买 Microsegment + Focus Group；Test Market 和 Concept Test 用满 | C5: 必买的报告；Test Market 份额预测很准 | D5: 买了 5 份 Microsegment + 5 份 Focus Group；Concept Test 10 次、Test Market 10 次全部用完
A6: 研发中心 1 | B6: 开始开发 Canyon（Utility，瞄准 5U，3 年后上市）；HP 尽量做到 225 以上 [推断] | C6: 练习轮单车利润最高的车 | D6: Canyon 66 / 245 HP / ISSQ 3-6-3-5，Y3 上市（Concept Test：245 best，225 sluggish，260 poor MPG）
A7: 研发中心 2 | B7: Cafav 直接做 major：尺寸往 38–40 改，Safety 和 Quality 往上加 | C7: 改成 40 后 Likely to buy 从 14.2% 升到 24.3% | D7: Cafav major 38 / 150 / Safety 4 / Quality 3（今年的上限），Y2 上市，上市时再调到 Safety 5
A8: 新研发中心 | B8: 马上建第 3、第 4 个；Y2 放 Crash major（68/200/S4/Q3）和 Cameo major（24，瞄准 2E） | C8: 新中心要等一年才能用；major 要占两年 | D8: 只建了第 3 个（$624M）：系统每年只能建 1 个中心
A9: 技术 | B9: Safety +1、Styling +1 先做 | C9: Cafav 要到 Safety 5，Canyon 要到 Styling 7 | D9: 只做 Safety +1（$327M）；Styling +1 推到 Y2 [推断：Canyon 上市那年还能调]
A10: 产能 | B10: 扩产 +500K（Y2 起能用） | C10: 扩产比超产便宜 | D10: +500K（$3,517M）
A11: 产量 | B11: Y1 最多排到产能的 110% [推断] | C11: Y1 超产 45%，超产能费 $1,544M | D11: 1,095K（109.5%），超产能费 $208M；Cafav 故意排得比需求少一点
A12: 价格 | B12: 每款车先用 Test Market 往上试 10%；Cafav 升级前 $21.8K 是断崖 | C12: 测试结果 | D12: Cafav $22,385、Crash $22,500、Cameo $12,640（都是 Test Market 测过的，约 +10%）
A13: 营销 | B13: 约占营收 2% | C13: Firm Preference 翻倍 | D13: 营销 $395M（约 1.8%）：Cafav 广告加倍 100/70、Crash 50/20，企业广告 $50M → $110M
A14: 融资 | B14: 增发到上限（约 $3.5B）+ 现金还掉 7.5% 的短贷；不发债；现金不宽裕不买 CD | C14: Y1 发债导致负债一直最高；Y3 买 CD 被强制借贷 | D14: 增发 $3,526M（上限）+ 还短贷 $4,000M，剩 $2,660M；不发债、不买 CD；分红 $100M
A15: 检查 | B15: Pro-Forma 三情景（卖出 90%、80%） | C15: Pro-Forma 每年都偏乐观 | D15: 做了：卖出 90% 现金约 $1.0B；卖出 80% 会被借约 $0.9B（也是 7.5%）
A16: Rationale | B16: 英文 → humanizer → 保存 | C16: 组里的规则 | D16: 已保存
A18: 之后每一年 | B18: 做法
A19: 缺货 | B19: 还在缺货就提价 10%，同时扩产（提前一年做）
A20: 车型升级当年 | B20: Test Market 会低估需求，排产要往上调；升级前一年少排产
A21: 第二款新车 | B21: 4M 高端 Minivan 或 5L 豪华车（单车毛利约 $7–9K）；不选 AEV、2M Minivan、3U Utility
A22: 债券 | B22: 出现 callable 就用增发的钱赎回
A23: 现金多了 | B23: 买 CD（最多 $10B）；分红的效果没测过
A24: 对手 | B24: 盯住 F 的 Utility 车，会来抢 Canyon 的 5U / 3U [推断]

Sheet 每年做了什么
A1: Firm C · StratSim 每年做了什么（练习 Y1–Y4 + 正式比赛）
A2: Year 1–4 都已出结果（Y4 于 10/6 出）。黄色列是 Year 4。每一行最后一列是一句话点评。 G 列是正式比赛 Year 1（10/11 已保存，10/14 截止后出结果）。 H 列是正式比赛 Year 2（10/16 保存）。 I 列是正式比赛 Year 3（10/17 保存）。
A4: 项目 | B4: Year 1 | C4: Year 2 | D4: Year 3 | E4: Year 4 | F4: 一句话点评 | G4: 正式 Y1（10/11 保存） | H4: 正式 Y2（10/16 保存） | I4: 正式 Y3（10/17 保存） | J4: 正式 Y4（10/25 保存，同日复查后修改） | K4: 正式 Y5（10/27 保存）
A5: 调研（每年必买：自己细分市场的 Microsegment + Focus Group）
A6: 买了哪些报告 | B6: 没买（违反要求） | C6: 12 份 Microsegment + 4 份 Focus Group + 7 次 Test Market | D6: 12 份 Microsegment + 4 份 Focus Group + 10 次 Test Market + 10 次 Concept Test + 3 份 Sales by Microsegment | E6: 5 份 Microsegment + 5 份 Focus Group（1E、2E、2F、3T、5U）+ 10 次 Concept Test + 10 次 Test Market | F6: Y3 起测试做满；Y4 的 Test Market 推翻了 Crash 降价 | G6: 5 份 Microsegment + 5 份 Focus Group（1E、2E、2F、3T、5U）+ 10 次 Concept Test + 10 次 Test Market | H6: 5 份 Microsegment + 5 份 Focus Group + 10 次 Concept Test + 10 次 Test Market | I6: Microsegment + Focus Group 8 份（加 3U、4F、5L）+ Sales by Microsegment 3 份 + 10 次 Concept Test + 10 次 Test Market（各留 2 次测最终组合） | J6: Microsegment + Focus Group 各 11 份（除 2M）；Test Market 10 次；Concept Test 10 次（第 10 次测 Cosmo $40K） | K6: Microsegment + Focus Group 各 11 份（除 2M）；Concept Test 9 次；Test Market 10 次（已用完）；10/28 加的 Cafav、Crash 营销没测
A7: 研发中心（每个中心每年都要放项目）
A8: 能用的中心数 | B8: 2 | C8: 2（第 3 个在建） | D8: 3（第 4 个在建） | E8: 4 | F8: 新中心今年建、明年才能用 | G8: 2（第 3 个在建） | H8: 3（第 4 个在建） | I8: 4（第 5 个在建，$643M） | J8: 5（全部在用） | K8: 5（全部在用）
A9: 中心 1 | B9: Canyon 开始开发（Utility 新车） | C9: Canyon 继续开发 | D9: Canyon 上市：64 / 200 HP | E9: Canyon minor：66 / 205 HP | F9: 提前开发新类别，Y3 进入没人做的 5U，份额 47.3% | G9: Canyon 开始开发：66 / 245 HP / 3-6-3-5 | H9: Canyon 继续开发（66 / 245，Y3 上市） | I9: Canyon 上市：66 / 245 / Styling 7 | J9: Canyon 降成本：$20,447 → $20,134，今年 $192M（65K 库存不报废） | K9: Cafav minor：Safety 5 → 6、Quality 4 → 5（2F 两个 hot button），Base Cost $15,137 → $15,270，$197M；56K 库存报废记 $89M
A10: 中心 2 | B10: Crash 降成本（单车省 $222） | C10: Cafav minor：Safety 4、Quality 2 | D10: Crash major 开始：68 / 200 HP / Styling 4 / Quality 3 | E10: Crash major 上市 | F10: Y1 用中心降成本不划算；Y2 只改 ISSQ 不改尺寸，Cafav 份额反而下降 | G10: Cafav major 开始：38 / 150 / Safety 4 / Quality 3 | H10: Cafav major 上市：40 / 150 / Safety 5 / Quality 4 | I10: 新车 Cosmo（Family，瞄准 4F）开始开发：56 / 190 / I4 / S3 / Sf5 / Q5，Y4 上市 | J10: Cosmo 上市（4F）：56 / 190 / Interior 5 / Safety 6，今年 $543M | K10: Canyon 降成本：$19,804 → $19,483，$197M
A11: 中心 3 | B11: — | C11: 开始建造 | D11: Cafav major 开始：28 → 38 | E11: Cafav major 上市，最后一年微调成 40 / Safety 5 / Quality 4 | F11: Concept Test：2F 的 Likely to buy 从 14.2% 升到 24.3%；但会失去 2E 的客户 | G11: 开始建造（$624M） | H11: Crash minor 上市：68 / 195 / Styling 3 / Quality 2 | I11: Crash 第二次 minor：Styling 4 / Quality 3 | J11: Cafav 降成本：$15,186 → $14,887（每辆省 $299），今年 $192M | K11: Crash 降成本：$14,059 → $13,819，$197M
A12: 中心 4 | B12: — | C12: — | D12: 开始建造（$643M） | E12: Cameo minor：14 / ISSQ 全部升到 2（处理 $103M 旧库存） | F12: ⚠️ 尺寸 14 在 1E 被评为 big、在 2E 被评为 too small，两头都不讨好 | G12: —（每年只能建 1 个中心） | H12: 开始建造（$630M） | I12: Cameo major 转 2E：22 / 125 / I2 / S2 / Sf3 / Q3，Y4 上市 | J12: 新 Cameo 上市（2E）：22 / 125 / Safety 4 / Quality 4，今年 $229M | K12: Cosmo 降成本：$21,448 → $21,144，$197M
A13: 中心 5 | B13: — | C13: — | D13: — | E13: — | G13: — | H13: — | I13: 开始建造（$643M），Y4 起能用 | J13: 新车 Chow（Sports，瞄准 3S）：40 / 205 / I2 / S7 / Sf3 / Q4，Base Cost $22,341，开发费 $1,318M（3 年），Y6 上市，今年 $439M（换掉 Crash 降成本） | K13: Chow 开发第 2 年（$439M），Y6 上市；Cameo 今年没有项目
A14: 技术投资 | B14: Styling +1（$300M） | C14: 不投 | D14: Safety +1（$263M） | E14: 不投（明年才生效） | F14: 为 Cafav 做到 Safety 5 做准备 | G14: Safety +1（$327M） | H14: Styling +1（$305M） | I14: Interior +1、Safety +1（$544M） | J14: 不买（原计划 Quality +1 $281M，复查后取消） | K14: Safety +1（$402M），为 Y6 Cafav、Cosmo 到 Safety 7
A15: 价格（MSRP）
A16: Cafav（家用车） | B16: 20750 | C16: 20900 | D16: 21500 | E16: 21500 | F16: 2F 的价格断崖在 $22K 左右 | G16: 22385 | H16: 24000 | I16: 26400 | J16: 29000 | K16: 30000
A17: Cameo（经济车） | B17: 11850 | C17: 13000 | D17: 14000 | E17: 14000 | F17: Y2 提价后照样卖光 | G17: 12640 | H17: 13900 | I17: 15290 | J17: 16500 | K17: 18150
A18: Crash（卡车） | B18: 20900 | C18: 22400 | D18: 23300 | E18: 23300 | F18: Test Market 显示降价都亏钱 | G18: 22500 | H18: 24000 | I18: 25500 | J18: 27000 | K18: 27000
A19: Canyon（Utility） | B19: — | C19: — | D19: 31000 | E19: 34000 | F19: 对价格几乎不敏感；Y3 定 $31K 还缺货超过 30% | G19: — | H19: —（Y3 上市） | I19: 39000 | J19: 39000 | K19: 40000
A20: Cosmo（家用车，4F） | B20: — | C20: — | D20: — | E20: — | G20: — | H20: — | I20: — | J20: 40000 | K20: 44000
A21: 营销和渠道
A22: 营销总额（$M） | B22: 225 | C22: 255 | D22: 760 | E22: 850 | F22: 老师要求占营收 2–4% | G22: 395 | H22: 675 | I22: 1105 | J22: 1555 | K22: 2213
A23: 营销占营收 | B23: =IFERROR(B22/每年的结果!B6,0) -> 0.0092539278 | C23: =IFERROR(C22/每年的结果!C6,0) -> 0.010479596 | D23: =IFERROR(D22/每年的结果!D6,0) -> 0.019853191 | E23: =IFERROR(E22/每年的结果!E6,0) -> 0.016342068 | F23: 公式：营销 ÷ 营收（营收取自“每年的结果”页；Y4 用 Pro-Forma 的营收） | G23: =IFERROR(G22/每年的结果!H6,0) -> 0.017230098 | H23: =IFERROR(H22/每年的结果!J6,0) -> 0.022461067 | I23: =IFERROR(I22/每年的结果!L6,0) -> 0.018600189 | J23: =IFERROR(J22/每年的结果!N6,0) -> 0.019933853 | K23: =IFERROR(K22/每年的结果!P6,0) -> 0.02496869
A24: 经销商 | B24: South +48 | C24: North +24、West +24 | D24: South +16 | E24: 不变（明年才生效） | F24: 总数 480 → 528 → 576 | G24: South +48 | H24: North +24、West +24 | I24: South +30、North +11、West +11（覆盖率 78.5%） | J24: North +16、South +16、East +8、West +16（覆盖率 78.5% → 85.5%） | K24: +62（10% 上限）：North 16、South 19、East 11、West 16；覆盖率 85.5% → 93.3%
A25: 经销商培训（$M） | B25: 15 | C25: 18 | D25: 30 | E25: 30 | F25: F 投 $30M，Firm Preference 最高 | G25: 11 | H25: 20 | I25: 30 | J25: 40 | K25: 45
A26: 生产和产能（千辆）
A27: 产能 | B27: 1000 | C27: 1500 | D27: 2000 | E27: 2200 | F27: 每年都在扩 | G27: 1000 | H27: 1500 | I27: 2250 | J27: 3050 | K27: 3450
A28: 排产合计 | B28: 1455 | C28: 1570 | D28: 1910 | E28: 2140 | F28: Y4 按“份额 × 全行业销量”来排 | G28: 1095 | H28: 1540 | I28: 2300 | J28: 2810 | K28: 3090
A29: 产能利用率 | B29: =IFERROR(B28/B27,0) -> 1.455 | C29: =IFERROR(C28/C27,0) -> 1.0466667 | D29: =IFERROR(D28/D27,0) -> 0.955 | E29: =IFERROR(E28/E27,0) -> 0.97272727 | F29: 公式：排产 ÷ 产能；超过 110% 就危险 | G29: =IFERROR(G28/G27,0) -> 1.095 | H29: =IFERROR(H28/H27,0) -> 1.0266667 | I29: =IFERROR(I28/I27,0) -> 1.0222222 | J29: =IFERROR(J28/J27,0) -> 0.92131148 | K29: =IFERROR(K28/K27,0) -> 0.89565217
A30: 超产能费（$M） | B30: 1544 | C30: 141 | D30: 0 | E30: 321 | F30: Y1 超产 45% 是最大的错误；Y4 四款车都缺货，Flex 自动多产 10%，超产 7%，付了 $321M | G30: 208 | H30: 79 | I30: 96 | J30: 0 | K30: 0
A31: 扩产（下一年生效） | B31: +500（$3,517M） | C31: +500（$3,439M） | D31: +200（$1,378M） | E31: 不扩（练习轮看不到效果） | F31: 正式比赛要提前一年扩 | G31: +500（$3,517M） | H31: +750（$5,126M，系统上限 50%） | I31: +800（$5,394M） | J31: +400（$2,711M；取消新车后照样扩，给老车型的增长用） | K31: +500（$3,430M），Y6 起 3,950K
A32: 融资
A33: 融资操作 | B33: 还清短贷 $6,660M，发债 $7,500M | C33: 不操作 → 系统自动借了 $2,492M 短贷（7.5%） | D33: 增发 $2,500M、还清短贷、买 $2,000M 的 CD → 现金不够，系统又自动借了 $751M | E33: 增发 $7,480M（上限是市值的 20%）→ 赎回 $7,500M 债券 + 还清 $751M 短贷 → 负债为 0；买 $3,000M 的 CD | F33: Y1 发债和 Y2 不融资都是错的；增发是对的 | G33: 增发 $3,526M（上限）+ 还短贷 $4,000M，剩 $2,660M；不发债、不买 CD | H33: 增发 $4,581M（上限）+ 还清短贷 $2,660M → 负债为 0 | I33: 不增发；买 $2,000M CD（3.0%）；负债 0 | J33: 不增发；买 $10,000M CD（3.5%，系统上限）；分红 $100M；负债 0 | K33: 不增发；CD 到期 $10,000M，再买 $10,000M（3.0%）；分红 $1,440M（每股 $2.00）；负债 0
A34: Rationale
A35: Decision Rationale | B35: — | C35: — | D35: 英文，用 humanizer 润色后保存 | E35: 英文，用 humanizer 润色后保存 | F35: 规则：每次都要先用 humanizer 再保存 | G35: 英文，用 humanizer 润色后保存 | H35: 英文，用 humanizer 润色后保存 | I35: 英文，用 humanizer 润色后保存 | J35: 英文，用 humanizer 润色后保存；署名 组员丙；10/25 改决策后重写 | K35: 英文，按 humanizer 规则润色后保存；署名 组员丁（用户 10/27 确认）

Sheet 每年的结果
A1: 每年的结果（$M，除非另有说明）
A2: Year 1–4 都是实际结果。Pro-Forma 是按“全部卖光”算的：Y2 实际比预测少 $692M，Y3 少 $695M；Y4 全部缺货、Flex 多卖了 214K 辆，所以实际反而比预测多 $600M。 H 列是正式比赛 Year 1 的实际结果（10/16 出），I 列是当时的 Pro-Forma 预测。 J 列是正式比赛 Year 2 的 Pro-Forma（10/16），实际结果 10/16 晚推进后补。 K 列是正式比赛 Year 2 的实际结果（10/17 出）。 L 列是正式比赛 Year 3 的 Pro-Forma（10/17）。
A4: 指标 | B4: Year 1 | C4: Year 2 | D4: Year 3 | E4: Year 4 | F4: Start（起点） | G4: 说明 | H4: 正式 Y1（实际） | I4: 正式 Y1（Pro-Forma） | J4: 正式 Y2（Pro-Forma） | K4: 正式 Y2（实际） | L4: 正式 Y3（Pro-Forma） | M4: 正式 Y3（实际） | N4: 正式 Y4（Pro-Forma） | O4: 正式 Y4（实际） | P4: 正式 Y5（Pro-Forma）
A5: 净利润 | B5: 679 | C5: 1165 | D5: 2999 | E5: 5265 | F5: 1201 | G5: 七家第 1（第 2 名 E 只有 $1,532M） | H5: 1318 | I5: 1237 | J5: 2663 | K5: 2945 | L5: 9680 | M5: 9242 | N5: 15262 | O5: 15578 | P5: 18251
A6: 营收 | B6: 24314 | C6: 24333 | D6: 38281 | E6: 52013 | F6: — | G6: 四款车全部缺货超过 30% | H6: 22925 | I6: 21931 | J6: 30052 | K6: 32507 | L6: 59408 | M6: 58444 | N6: 78008 | O6: 79035 | P6: 88631
A7: 净利率 | B7: =IFERROR(B5/B6,0) -> 0.027926298 | C7: =IFERROR(C5/C6,0) -> 0.047877368 | D7: =IFERROR(D5/D6,0) -> 0.078341736 | E7: =IFERROR(E5/E6,0) -> 0.10122469 | F7: — | G7: 公式：净利润 ÷ 营收；老师要求至少 4.5% | H7: =IFERROR(H5/H6,0) -> 0.057491821 | I7: =IFERROR(I5/I6,0) -> 0.056404177 | J7: =IFERROR(J5/J6,0) -> 0.088613071 | K7: =IFERROR(K5/K6,0) -> 0.090595872 | L7: =IFERROR(L5/L6,0) -> 0.16294102 | M7: =IFERROR(M5/M6,0) -> 0.15813428 | N7: =IFERROR(N5/N6,0) -> 0.1956466 | O7: =IFERROR(O5/O6,0) -> 0.19710255 | P7: =IFERROR(P5/P6,0) -> 0.20592118
A8: 累计净利润 | B8: =F5+B5 -> 1880 | C8: =B8+C5 -> 3045 | D8: =C8+D5 -> 6044 | E8: =D8+E5 -> 11309 | F8: — | G8: 公式：按系统 Dashboard 的口径（含 Start 年） | H8: =F5+H5 -> 2519 | I8: — | J8: — | K8: =H8+K5 -> 5464 | L8: — | M8: =K8+M5 -> 14706 | N8: — | O8: =M8+O5 -> 30284 | P8: —
A9: Pro-Forma 预测的净利润 | B9: — | C9: 1857 | D9: 3694 | E9: 4665 | F9: — | G9: 每年都偏乐观 | H9: 1237 | I9: — | J9: — | K9: 2663 | L9: — | M9: 9680 | N9: — | O9: 15262 | P9: —
A10: 实际 − 预测 | B10: — | C10: =C5-C9 -> -692 | D10: =D5-D9 -> -695 | E10: =E5-E9 -> 600 | F10: — | G10: 公式：负数表示 Pro-Forma 高估了 | H10: =H5-H9 -> 81 | I10: — | J10: — | K10: =K5-K9 -> 282 | L10: — | M10: =M5-M9 -> -438 | N10: — | O10: =O5-O9 -> 316 | P10: —
A11: 股价（$） | B11: 35.16 | C11: 39.25 | D11: 66.38 | E11: 90.71 | F11: 35.26 | G11: Y4 增发了 1.12 亿股，股价还是涨了 37% | H11: 38.18 | I11: — | J11: — | K11: 55.09 | L11: — | M11: 104.63 | N11: — | O11: 156.75 | P11: —
A12: 市值 | B12: 17600 | C12: 19625 | D12: 37418 | E12: 61354 | F12: — | G12: 七家第 1，是第 2 名 F（$30.9B）的 2 倍 | H12: 22908 | I12: — | J12: — | K12: 39664 | L12: — | M12: 75332 | N12: — | O12: 112857 | P12: —
A13: Firm Preference | B13: 0.118 | C13: 0.108 | D13: 0.204 | E13: 0.338 | F13: 0.143 | G13: 第 1（F 17.7% 第二） | H13: 0.124 | I13: — | J13: — | K13: 0.194 | L13: — | M13: 0.225 | N13: — | O13: 0.257 | P13: —
A14: 库存天数 | B14: 34 | C14: 60 | D14: 60 | E14: 0 | F14: — | G14: 四款车全部卖光 | H14: 2 | I14: 2 | J14: 1 | K14: 0 | L14: 0 | M14: 10 | N14: 0 | O14: 9 | P14: 0
A15: 期末现金 | B15: 448 | C15: 243 | D15: 383 | E15: 8783 | F15: 2093 | G15: 另有 $3,000M 的 CD；没有被系统借贷 | H15: 1332 | I15: 1268 | J15: 1024 | K15: 1400 | L15: 3959 | M15: 2332 | N15: 9274 | O15: 8564 | P15: 24502
A16: 总负债 | B16: — | C16: 9992 | D16: 8251 | E16: 0 | F16: — | G16: 债券全部赎回，短贷还清 | H16: 2660 | I16: 2660 | J16: 0 | K16: 0 | L16: 0 | M16: 0 | N16: 0 | O16: 0 | P16: 0

Sheet 正式Y1复盘
A1: 正式 Year 1 结果复盘（10/16 出结果）
A2: 七家里排第 2（净利、市值都是第 2，第 1 名 G）。下面是：我们怎么预测的、实际多少、为什么有差距；每个数据为什么涨跌；同行业为什么是他们第一。和 md 0c 节“正式 Year 1 结果复盘”同步。[推断] 是推出来的，系统没有直接给。
A4: A. 我们的预测 vs 实际（每一项是怎么预测的、为什么有差距）
A5: 项目 | B5: 怎么预测的 | C5: 预测 | D5: 实际 | E5: 差距 | F5: 原因
A6: 全行业销量（千辆） | B6: 练习轮 Y2、Y3 实际 10,078–10,339K，系统预测 10,499K 打折 | C6: 10100 | D6: 8961 | E6: =D6-C6 -> -1139 | F6: 每家产能只有 1,000K，大家都少产、提价，市场被全行业的产量卡住
A7: Cafav 份额 | B7: Test Market：$22,385 + 广告 100 / 70 | C7: 0.053 | D7: 0.06 | E7: =D7-C7 -> 0.007 | F7: Test Market 假设对手不改价，实际对手也提价了
A8: Crash 份额 | B8: Test Market：$22,500 + 广告 50 / 20 | C8: 0.041 | D8: 0.049 | E8: =D8-C8 -> 0.008 | F8: 同上；Boss、Fast $22,000，Dusty $24,000
A9: Cameo 份额 | B9: Test Market：$12,640 | C9: 0.029 | D9: 0.034 | E9: =D9-C9 -> 0.005 | F9: 同上；Cameo 现在是 2E 的第一名
A10: 销量合计（千辆） | B10: 份额 × 10,100K | C10: 1230 | D10: 1287 | E10: =D10-C10 -> 57 | F10: 份额低估 + 行业规模高估，两边抵消后还多卖了 57K
A11: Cafav 销量（千辆） | B11: 份额 × 10,100K | C11: 530 | D11: 541 | E11: =D11-C11 -> 11 | F11: 同上
A12: Crash 销量（千辆） | B12: 份额 × 10,100K | C12: 410 | D12: 440 | E12: =D12-C12 -> 30 | F12: 同上
A13: Cameo 销量（千辆） | B13: 份额 × 10,100K | C13: 290 | D13: 306 | E13: =D13-C13 -> 16 | F13: 同上
A14: 产量（千辆） | B14: 排产 1,095K + Pro-Forma 估 Flex 21K | C14: 1116 | D14: 1174 | E14: =D14-C14 -> 58 | F14: Flex 看到需求多，自动加产（Cameo 加满 10%）
A15: 超产能费（$M） | B15: Manufacturing 页面读数；按 1,116K 约 $260M [推断] | C15: 260 | D15: 421 | E15: =D15-C15 -> 161 | F15: Flex 多产 58K，超产到 117%
A16: 营收（$M） | B16: Pro-Forma | C16: 21931 | D16: 22925 | E16: =D16-C16 -> 994 | F16: 多卖 57K 辆，价格不变
A17: COGS（$M） | B17: Pro-Forma | C17: 16832 | D17: 17679 | E17: =D17-C17 -> 847 | F17: 多卖车的变动成本约 $700M + 多付的超产能费约 $160M
... A22: 期末库存（千辆） | B22: Pro-Forma | C22: 7 | D22: 8 | E22: =D22-C22 -> 1 | F22: 基本准
A23: 股价 | B23: 没有单独预测 | C23: — | D23: 38.18 | E23: — | F23: 净利上升、负债下降；增发没有压低股价
A24: Firm Preference | B24: 练习轮经验：营销约占营收 2% 会让偏好度上升 | C24: 上升 | D24: 0.124 | E24: −1.9 点 | F24: [推断] 今年没有新车或升级车上市；营销只占 1.7%
A26: B. 每个数据为什么涨、为什么跌（Start → Year 1）
A27: 项目 | B27: Start | C27: Year 1 | D27: 变化 | E27: 原因
A28: 营收（$M） | B28: 23828 | C28: 22925 | D28: =IFERROR((C28-B28)/B28,"—") -> -0.037896592 | E28: 销量 1,452K → 1,287K（产能只有 1,000K，不再超产 43%）；价格都提了约 10%
A29: COGS（$M） | B29: 20319 | C29: 17679 | D29: =IFERROR((C29-B29)/B29,"—") -> -0.12992765 | E29: 少产了车；超产能费 $1,400M → $421M
A30: 毛利率 | B30: 0.147 | C30: 0.229 | D30: =C30-B30 -> 0.082 | E30: 提价 + 超产能费大降；七家里最高
A31: 营销（$M） | B31: 215 | C31: 395 | D31: =IFERROR((C31-B31)/B31,"—") -> 0.8372093 | E31: 广告加倍（Cafav 100 / 70、Crash 50 / 20），企业广告 $50M → $110M
A32: 研发（$M） | B32: 0 | C32: 1627 | D32: =IFERROR((C32-B32)/B32,"—") -> — | E32: Canyon $506M、Cafav major $169M、第 3 个研发中心 $624M、Safety 技术 $327M
A33: G&A（$M） | B33: 948 | C33: 994 | D33: =IFERROR((C33-B33)/B33,"—") -> 0.048523207 | E33: 新开 48 家经销商的开店费和管理费 [推断]
A34: 营业利润（$M） | B34: 2347 | C34: 2229 | D34: =IFERROR((C34-B34)/B34,"—") -> -0.050276949 | E34: 毛利多了约 $1,700M，但研发多花 $1,627M
A35: 利息（$M） | B35: 500 | C35: 200 | D35: =IFERROR((C35-B35)/B35,"—") -> -0.6 | E35: 还掉 $4,000M 的 7.5% 短贷
A36: 净利（$M） | B36: 1201 | C36: 1318 | D36: =IFERROR((C36-B36)/B36,"—") -> 0.097418818 | E36: 毛利 +、利息 −，研发投入 +
A37: EPS（$） | B37: 2.4 | C37: 2.2 | D37: =IFERROR((C37-B37)/B37,"—") -> -0.083333333 | E37: 股数 500M → 600M（净利 +9.7%，股数 +20%）
A38: 净利率（ROS） | B38: 0.05 | C38: 0.057 | D38: =C38-B38 -> 0.007 | E38: 净利涨、营收跌
A39: 现金（$M） | B39: 2093 | C39: 1332 | D39: =IFERROR((C39-B39)/B39,"—") -> -0.36359293 | E39: 经营现金流 +3,330、增发 +3,526；扩产 −3,517、还短贷 −4,000、分红 −100
A40: 库存（$M） | B40: 1713 | C40: 124 | D40: =IFERROR((C40-B40)/B40,"—") -> -0.92761238 | E40: Start 的 121K 辆库存全部卖掉，库存天数 30 → 2
A41: 厂房设备（$M） | B41: 7619 | C41: 11136 | D41: =IFERROR((C41-B41)/B41,"—") -> 0.46160914 | E41: 扩产 +500K（$3,517M），Y2 起可用
A42: 短贷（$M） | B42: 6660 | C42: 2660 | D42: =IFERROR((C42-B42)/B42,"—") -> -0.6006006 | E42: 还了 $4,000M
A43: 股东权益（$M） | B43: 2181 | C43: 6925 | D43: =IFERROR((C43-B43)/B43,"—") -> 2.175149 | E43: 增发 $3,526M + 净利 $1,318M − 分红 $100M
A44: ROE | B44: 0.551 | C44: 0.19 | D44: =C44-B44 -> -0.361 | E44: 权益变成原来的 3 倍多（分母变大），不是赚得少了
A45: 股价（$） | B45: 35.26 | C45: 38.18 | D45: =IFERROR((C45-B45)/B45,"—") -> 0.082813386 | E45: 净利上升、负债下降
A46: 市值（$M） | B46: 17630 | C46: 22908 | D46: =IFERROR((C46-B46)/B46,"—") -> 0.29937606 | E46: 增发 + 股价上涨
A47: Firm Preference | B47: 0.143 | C47: 0.124 | D47: =C47-B47 -> -0.019 | E47: [推断] 对手升级了车（D、G 各 2 款），我们的 major 要 Y2、Y3 才上市
A48: Cafav 销量（千辆） | B48: 703 | C48: 541 | D48: =IFERROR((C48-B48)/B48,"—") -> -0.23044097 | E48: 提价 10% + 故意少排产（Y2 新版上市时旧库存要亏本处理）
A49: Cafav 贡献（$M） | B49: 3012 | C49: 3145 | D49: =IFERROR((C49-B49)/B49,"—") -> 0.044156707 | E49: 单车售价 $17,908 → $19,688，少卖 162K 辆贡献反而多了
A50: Crash 销量（千辆） | B50: 444 | C50: 440 | D50: =IFERROR((C50-B50)/B50,"—") -> -0.009009009 | E50: 提价 9.8% + 广告加倍，销量几乎不变
A51: Crash 贡献（$M） | B51: 2249 | C51: 2932 | D51: =IFERROR((C51-B51)/B51,"—") -> 0.30369053 | E51: 单车售价 $18,038 → $19,811
A52: Cameo 销量（千辆） | B52: 304 | C52: 306 | D52: =IFERROR((C52-B52)/B52,"—") -> 0.0065789474 | E52: 提价 10% 销量不变，说明 Cameo 定价太低
A53: Cameo 贡献（$M） | B53: 290 | C53: 584 | D53: =IFERROR((C53-B53)/B53,"—") -> 1.0137931 | E53: 单车售价 $10,573 → $11,621，贡献翻倍
A54: 三款车贡献合计（$M） | B54: 5551 | C54: 6661 | D54: =IFERROR((C54-B54)/B54,"—") -> 0.19996397 | E54: 提价 + 加广告
A55: FCF（$M） | B55: — | C55: -187 | D55: — | E55: 经营现金流 $3,330M − 扩产 $3,517M；为 Canyon 准备产能，是一次性的
A57: C. 七家对比（Year 1）和为什么是他们第一
A58: 公司 | B58: 净利（$M） | C58: 毛利率 | D58: 营销（$M） | E58: 研发（$M） | F58: 利息（$M） | G58: 股价 | H58: 市值（$M） | I58: 总负债（$M） | J58: 偏好度 | K58: 库存（千辆） | L58: 今年做了什么
A59: A | B59: 278 | C59: 0.159 | D59: 215 | E59: 1657 | F59: 500 | G59: 30.26 | H59: 15130 | I59: 6660 | J59: 0.147 | K59: 0 | L59: 升级 Alfa；没还债、没增发；扩产 +100K
A60: B | B60: 767 | C60: 0.196 | D60: 420 | E60: 1269 | F60: 385 | G60: 33.26 | H60: 19931 | I60: 5660 | J60: 0.096 | K60: 0 | L60: 增发 $3.5B + 发债 $2B，还短贷 $3B；扩产 +500K
A61: C（我们） | B61: 1318 | C61: 0.229 | D61: 395 | E61: 1627 | F61: 200 | G61: 38.18 | H61: 22908 | I61: 2660 | J61: 0.124 | K61: 8 | L61: 增发 $3.5B，还短贷 $4B；扩产 +500K
A62: D | B62: 1118 | C62: 0.198 | D62: 217 | E62: 1030 | F62: 543 | G62: 36.71 | H62: 18355 | I62: 8034 | J62: 0.203 | K62: 286 | L62: 升级 Defy、Dusty；发债 $3B、没增发；压了 81 天库存；扩产 +300K
A63: E | B63: 1037 | C63: 0.182 | D63: 460 | E63: 1300 | F63: 125 | G63: 38.07 | H63: 22814 | I63: 1660 | J63: 0.13 | K63: 7 | L63: 增发 $3.5B，还短贷 $5B；营销最多；营收和销量第一；扩产 +300K
A64: F | B64: 853 | C64: 0.223 | D64: 360 | E64: 1965 | F64: 310 | G64: 34.87 | H64: 20896 | I64: 4660 | J64: 0.106 | K64: 0 | L64: 增发 $3.5B + 发债 $2B，还短贷 $4B；研发最多，多买 Quality 技术；扩产 +400K
A65: G | B65: 2014 | C65: 0.216 | D65: 215 | E65: 364 | F65: 172 | G65: 38.8 | H65: 23280 | I65: 3134 | J65: 0.194 | K65: 53 | L65: 升级 Gas、Gone；增发 $3.5B + 发债 $3.1B，短贷全部还清；没建研发中心、没买技术、没分红；扩产 +300K
A66: G 净利第一 | B66: 几乎没投资：研发只有 $364M（我们 $1,627M，差 $1,263M，税后约 $821M）；营业利润率最高（14.9%）；用增发 + 发债把短贷全还了，利息最低（$172M）；升级了 2 款车，偏好度第 2。[推断] 我们如果不投资，净利约 $2,139M，会超过 G
A67: G 市值第一 | B67: 股数和我们一样（都是 600M），差在股价 $38.80 vs $38.18，主要因为净利高
A68: G 能不能保持 | B68: [推断] 只有 2 个研发中心，也没有新车在开发；我们 Y2 Cafav 新版上市、Y3 Canyon 进入没有竞争的 5U
A69: E 营收和销量第一 | B69: 营销最多（$460M），Egad 是 1T 和 2M 的第一名；毛利率只有 18.2%，价格定得低，净利只有 $1,037M
A70: D 偏好度第一 | B70: 升级了 Defy、Dusty（Dusty 是 5U 第一）；但压了 286K 辆库存（$4.27B），现金只剩 $229M，负债 $8.0B 七家最高
A71: A 最后一名 | B71: 短贷一分没还（利息 $500M）；毛利率只有 15.9%；净利 $278M，股价跌了 $5
A73: D. 我们的问题和教训
A74: 问题 | B74: 证据 | C74: 下一年怎么改
A75: 价格定低了 | B75: 三款车份额都比 Test Market 高 0.5–0.8 点，全部卖光，Cameo 的 Flex 加满；[推断] Crash 再贵 $1,000 也卖得完，少赚约 $3.9 亿 | C75: Test Market 测出来的价格再往上加；只要还缺货就继续提
A76: Firm Preference 降到第 5 | B76: 14.3% → 12.4%；D、G 升级车型后排前两名，营销费和偏好度没有明显关系 | C76: Cafav 新版上市当年多投营销，营销提到营收的 2% 以上
A77: 超产到 117% | B77: Flex 多产 79K，超产能费 $421M；Cameo 多产的部分亏钱 | C77: 关掉 Cameo 的 Flex
A78: 不算问题：净利输给 G | B78: G 的研发只有 $364M，我们为 Canyon、Cafav 新版、研发中心、技术投了 $1,627M | C78: 投资在 Y2、Y3 见效
A79: 不算问题：增发优势没了 | B79: B、E、F、G 也都增发到约 600M 股 | C79: 市值拼股价，股价拼净利
A81: E. 年度财务目标（Cheat Sheet #4，BoD presentation 要汇报）
A82: 目标 | B82: 结果 | C82: 达标 | D82: 解释
A83: 营收增长 | B83: $23,828M → $22,925M（−3.8%） | C83: ❌ | D83: 行业 −13%，我们只 −3.8%；主动少产车、提价换利润
A84: 毛利率 ≥ 10%，保持或提高 | B84: 14.7% → 22.9% | C84: ✅ | D84: 七家最高
A85: 净利率 ≥ 4.5%，保持或提高 | B85: 5.0% → 5.7% | C85: ✅
A86: FCF 为正 | B86: −$187M | C86: ❌ | D86: 扩产 $3.5B 为 Canyon 准备产能
A87: ROE ≥ 10%，保持或提高 | B87: 55% → 19% | C87: ⚠️ | D87: 超过 10%，但因为增发、权益变大而下降
A88: 市值增长 | B88: $17.6B → $22.9B（+30%） | C88: ✅ | D88: 增发 + 股价 +8.3%

Sheet 正式Y2复盘
A1: 正式 Year 2 结果复盘（10/17 出结果）
A2: 净利、市值、股价、份额全部第 1。下面是：我们怎么预测的、实际多少、为什么有差距；每个数据为什么涨跌；同行业为什么现在是我们第一；问题和教训。和 md 0c 节“正式 Year 2 结果复盘”同步。[推断] 是推出来的，系统没有直接给。
A4: A. 我们的预测 vs 实际
A5: 项目 | B5: 怎么预测的 | C5: 预测 | D5: 实际 | E5: 差距 | F5: 原因
A6: 全行业销量（千辆） | B6: 全行业产能约 9,400K × 约 1.1 [推断] | C6: 10500 | D6: 9519 | E6: =D6-C6 -> -981 | F6: A、D、G 压了约 81 万辆库存；实际是系统预测 12,388K 的 77%
A7: Cafav 份额 | B7: Test Market 旧版 5.6% + 升级 1.2 点 [推断] | C7: 0.068 | D7: 0.083 | E7: =D7-C7 -> 0.015 | F7: 新版升级效果被低估（实际比旧版高 2.7 点）；还被产量卡住，缺货 >30%
A8: Crash 份额 | B8: Test Market 旧版 + 升级 0.5 点 [推断] | C8: 0.049 | D8: 0.055 | E8: =D8-C8 -> 0.006 | F8: minor 后尺寸、HP 对上；和 Dusty 同价、配置更好
A9: Cameo 份额 | B9: Test Market | C9: 0.033 | D9: 0.038 | E9: =D9-C9 -> 0.005 | F9: [推断] Cafav 离开 2E，客户转到 Cameo
A10: 销量合计（千辆） | B10: 份额 × 10,500K | C10: 1559 | D10: 1682 | E10: =D10-C10 -> 123 | F10: 份额低估抵消了行业规模高估还有余
A11: Cafav 销量（千辆） | B11: 同上 | C11: 714 | D11: 792 | E11: =D11-C11 -> 78 | F11: Flex 加满（720 × 1.1）
A12: Crash 销量（千辆） | B12: 同上 | C12: 500 | D12: 528 | E12: =D12-C12 -> 28 | F12: Flex 加满（480 × 1.1）
A13: Cameo 销量（千辆） | B13: 同上 | C13: 345 | D13: 362 | E13: =D13-C13 -> 17 | F13: Flex 加了 22K（提交前改回开启是对的）
A14: 超产能费（$M） | B14: Manufacturing 页面按排产 1,540K 读数 | C14: 79 | D14: 400 | E14: =D14-C14 -> 321 | F14: Flex 加满后产量 1,682K（112%）
A15: 营收（$M） | B15: Pro-Forma | C15: 30052 | D15: 32507 | E15: =D15-C15 -> 2455 | F15: 多卖 123K 辆
A16: COGS（$M） | B16: Pro-Forma | C16: 22255 | D16: 24225 | E16: =D16-C16 -> 1970 | F16: 多卖车的变动成本 + 多付的超产能费
A17: 毛利率 | B17: Pro-Forma | C17: 0.259 | D17: 0.255 | E17: =D17-C17 -> -0.004 | F17: 超产能费比预计多
... A20: 期末现金（$M） | B20: Pro-Forma | C20: 1024 | D20: 1400 | E20: =D20-C20 -> 376 | F20: 净利多了
A21: Firm Preference | B21: [推断] 升级车型上市会拉高偏好度 | C21: 上升 | D21: 0.194 | E21: +7.0 点 | F21: ✅ 验证：两款升级上市 + 营销七家最多
A22: 股价（$） | B22: 没有单独预测 | C22: — | D22: 55.09 | E22: +44% | F22: 净利翻倍多、负债为 0、份额第一
A23: 三情景 | B23: startup-financial-modeling | C23: 乐观 110% 净利约 $2,927M | D23: 卖到基准的 108% | E23: — | F23: 落在乐观情景，净利和乐观情景几乎一样
A25: B. 每个数据为什么涨、为什么跌（Year 1 → Year 2）
A26: 项目 | B26: Year 1 | C26: Year 2 | D26: 变化 | E26: 原因
A27: 营收（$M） | B27: 22925 | C27: 32507 | D27: =IFERROR((C27-B27)/B27,"—") -> 0.41797165 | E27: 产能 1,000K → 1,500K，销量 +31%；三款车都提价 7–10%
A28: COGS（$M） | B28: 17679 | C28: 24225 | D28: =IFERROR((C28-B28)/B28,"—") -> 0.37026981 | E28: 销量增加；Cafav 新版单车成本 $13,560 → $14,885
A29: 毛利率 | B29: 0.229 | C29: 0.255 | D29: =C29-B29 -> 0.026 | E29: 提价 + 高毛利车型占比更高
A30: 营销（$M） | B30: 395 | C30: 675 | D30: =IFERROR((C30-B30)/B30,"—") -> 0.70886076 | E30: Cafav 新版上市广告加倍；企业广告 $110M → $150M
A31: 研发（$M） | B31: 1627 | C31: 1868 | D31: =IFERROR((C31-B31)/B31,"—") -> 0.14812538 | E31: Canyon $506M、Cafav $222M、Crash minor $205M、第 4 个中心 $630M、Styling $305M
A32: G&A（$M） | B32: 994 | C32: 1193 | D32: =IFERROR((C32-B32)/B32,"—") -> 0.20020121 | E32: South 新开 48 家经销商的管理费；培训费 $11M → $20M
A33: 营业利润（$M） | B33: 2229 | C33: 4546 | D33: =IFERROR((C33-B33)/B33,"—") -> 1.0394796 | E33: 毛利多了约 $3,000M，费用只多了约 $700M
A34: 利息（$M） | B34: 200 | C34: 0 | D34: =IFERROR((C34-B34)/B34,"—") -> -1 | E34: 短贷全部还清
A35: 净利（$M） | B35: 1318 | C35: 2945 | D35: =IFERROR((C35-B35)/B35,"—") -> 1.2344461 | E35: 上面几项合起来
A36: EPS（$） | B36: 2.2 | C36: 4.09 | D36: =IFERROR((C36-B36)/B36,"—") -> 0.85909091 | E36: 股数 +20%，净利 +123%
A37: 净利率（ROS） | B37: 0.057 | C37: 0.091 | D37: =C37-B37 -> 0.034 | E37: —
A38: 现金（$M） | B38: 1332 | C38: 1400 | D38: =IFERROR((C38-B38)/B38,"—") -> 0.051051051 | E38: 经营现金流 +4,437、增发 +4,581；扩产 −5,126、retooling −1,064、还短贷 −2,660、分红 −100
A39: 应收账款（$M） | B39: 1788 | C39: 2560 | D39: =IFERROR((C39-B39)/B39,"—") -> 0.43176734 | E39: 销售额增加
A40: 厂房设备（$M） | B40: 11136 | C40: 17326 | D40: =IFERROR((C40-B40)/B40,"—") -> 0.55585489 | E40: 扩产 +750K + retooling
A41: 负债（$M） | B41: 2660 | C41: 0 | D41: =IFERROR((C41-B41)/B41,"—") -> -1 | E41: 增发的钱还清短贷
A42: 股东权益（$M） | B42: 6925 | C42: 14351 | D42: =IFERROR((C42-B42)/B42,"—") -> 1.0723466 | E42: 增发 $4,581M + 净利 $2,945M − 分红 $100M
A43: ROE | B43: 0.19 | C43: 0.205 | D43: =C43-B43 -> 0.015 | E43: 净利涨得比权益快
A44: 股价（$） | B44: 38.18 | C44: 55.09 | D44: =IFERROR((C44-B44)/B44,"—") -> 0.44290204 | E44: 净利翻倍多、负债为 0
A45: 市值（$M） | B45: 22908 | C45: 39664 | D45: =IFERROR((C45-B45)/B45,"—") -> 0.73144753 | E45: 股价上涨 + 增发
A46: Firm Preference | B46: 0.124 | C46: 0.194 | D46: =C46-B46 -> 0.07 | E46: 两款升级车上市 + 营销七家最多
A47: 销量份额 | B47: 0.144 | C47: 0.177 | D47: =C47-B47 -> 0.033 | E47: 产能更大 + 新版 Cafav
A48: Cafav 销量（千辆） | B48: 541 | C48: 792 | D48: =IFERROR((C48-B48)/B48,"—") -> 0.46395564 | E48: 新版 40 / Sf5 / Q4，2F 和 3S 第一，缺货 >30%
A49: Cafav 贡献（$M） | B49: 3145 | C49: 4598 | D49: =IFERROR((C49-B49)/B49,"—") -> 0.46200318 | E49: $22,385 → $24,000
A50: Crash 销量（千辆） | B50: 440 | C50: 528 | D50: =IFERROR((C50-B50)/B50,"—") -> 0.2 | E50: minor 68 / 195，5U 和 4L 第一
A51: Crash 贡献（$M） | B51: 2932 | C51: 4042 | D51: =IFERROR((C51-B51)/B51,"—") -> 0.37858117 | E51: $22,500 → $24,000
A52: Cameo 销量（千辆） | B52: 306 | C52: 362 | D52: =IFERROR((C52-B52)/B52,"—") -> 0.18300654 | E52: 提价 10% 销量反而 +18%（Flex 开着）
A53: Cameo 贡献（$M） | B53: 584 | C53: 1099 | D53: =IFERROR((C53-B53)/B53,"—") -> 0.88184932 | E53: $12,640 → $13,900
A54: FCF（$M） | B54: -187 | C54: -1753 | D54: — | E54: 经营现金流 $4,437M − 扩产和 retooling $6,190M；为 Canyon 准备产能
A56: C. 七家对比（Year 2）和为什么现在是我们第一
A57: 公司 | B57: 净利（$M） | C57: 毛利率 | D57: 营销（$M） | E57: 研发（$M） | F57: 利息（$M） | G57: 股价 | H57: 市值（$M） | I57: 总负债（$M） | J57: 偏好度 | K57: 销量份额 | L57: 库存（千辆） | M57: 今年做了什么
A58: A | B58: 1806 | C58: 0.26 | D58: 215 | E58: 944 | F58: 480 | G58: 36 | H58: 18000 | I58: 6000 | J58: 0.121 | K58: 0.108 | L58: 280 | M58: 升级 Alfa、Ace；宣布做 Utility；份额 15.4% → 10.8%；经营现金流 −$1,187M
A59: B | B59: 2068 | C59: 0.205 | D59: 485 | E59: 501 | F59: 226 | G59: 43.78 | H59: 26236 | I59: 3660 | J59: 0.202 | K59: 0.152 | L59: 0 | M59: 升级 Buzzy、Boffo、Boss 三款；不分红；偏好度第一
A60: C（我们） | B60: 2945 | C60: 0.255 | D60: 675 | E60: 1868 | F60: 0 | G60: 55.09 | H60: 39664 | I60: 0 | J60: 0.194 | K60: 0.177 | L60: 0 | M60: Cafav major、Crash minor 上市；增发还清负债；扩产 +750K
A61: D | B61: 1205 | C61: 0.236 | D61: 217 | E61: 1370 | F61: 568 | G61: 37.02 | H61: 18510 | I61: 8034 | J61: 0.096 | K61: 0.132 | L61: 343 | M61: 升级 Defy；一次性损失 $285M；99 天库存
A62: E | B62: 1459 | C62: 0.183 | D62: 460 | E62: 859 | F62: 40 | G62: 40.93 | H62: 24528 | I62: 660 | J62: 0.148 | K62: 0.15 | L62: 0 | M62: 升级 Efizz、Egad；宣布做 Utility
A63: F | B63: 1603 | C63: 0.205 | D63: 525 | E63: 855 | F63: 296 | G63: 40.69 | H63: 24384 | I63: 4660 | J63: 0.12 | K63: 0.142 | L63: 45 | M63: 升级 Fantasy；宣布做 Utility；培训费最多；Interior 5、Quality 7
A64: G | B64: 1867 | C64: 0.204 | D64: 215 | E64: 389 | F64: 172 | G64: 40.29 | H64: 24174 | I64: 3134 | J64: 0.118 | K64: 0.138 | L64: 191 | M64: 升级 Gas、Gone；不分红；只有 2 个研发中心；53 天库存
A65: 我们第一的原因 | B65: Cafav 新版是最好的家用车（40 / Sf5 / Q4），同级最高价 $24,000 还缺货 >30%，2F 和 3S 第一；Crash 是 5U 和 4L 第一；负债和利息为 0；营销最多 + 两款升级，偏好度第 2；产能 1,500K + Flex，卖得最多
A66: G 为什么掉下来 | B66: 研发只有 $389M、没有新车；压了 $2.7B 库存；偏好度 19.4% → 11.8%
A67: B 为什么第二 | B67: 一年升级 3 款车（都是 minor，研发只花 $501M），偏好度第一；不分红
A68: A、D 的问题 | B68: 都压了 99 天库存（A $4.2B、D $4.9B），负债 $6.0B、$8.0B；A 毛利率 26.0% 是因为成本留在库存里 [推断]
A70: D. 问题和教训
A71: 问题 | B71: 证据 | C71: 下一年怎么改
A72: Cafav 又定低了、产少了 | B72: 缺货 >30%，[推断] 真实需求超过 103 万辆；Concept Test 的断崖夸大了价格敏感度；升级效果 +2.7 点（假设 +1.2） | C72: Y3 用 Test Market（现在测的是新版）往上提价
A73: 超产到 112% | B73: Flex 加满，超产能费 $400M；每辆车毛利都高于超产成本 | C73: Y3 产能 2,250K，Canyon 上市后还会紧，再扩产
A74: 全行业规模又估高了 | B74: 10,500K vs 9,519K；A、D、G 压库存 | C74: [推断] 他们可能降价清库存，盯住价格
A75: Dealer Rating 降到 66 | B75: 其他家多是 67 | C75: Y3 提高培训费
A76: A、E、F 宣布做 Utility | B76: 最早 Y4 上市 [推断] | C76: Canyon Y3 先独占 5U，Y4 准备竞争
A78: E. 年度财务目标
A79: 目标 | B79: 结果 | C79: 达标
A80: 营收增长 | B80: +41.8% | C80: ✅
A81: 毛利率 ≥ 10%，保持或提高 | B81: 22.9% → 25.5% | C81: ✅
A82: 净利率 ≥ 4.5%，保持或提高 | B82: 5.7% → 9.1% | C82: ✅
A83: FCF 为正 | B83: −$1,753M（为 Canyon 扩产） | C83: ❌
A84: ROE ≥ 10%，保持或提高 | B84: 19.0% → 20.5% | C84: ✅
A85: 市值增长 | B85: +73% | C85: ✅

Sheet 正式Y3复盘
A1: 正式 Year 3 结果复盘（10/24 出结果）
A2: 七家第 1，领先拉得更大：Weighted Score 98.2（第 2 名 F 79.0）；净利 $9,242M（第 2 名 F $3,399M）；累计净利 $14,706M（第 2 名 B $7,210M）；市值 $75.3B（第 2 名 F $36.0B）；销量份额和 Firm Preference 都是 22.5%，第 1。下面是：我们怎么预测的、实际多少、为什么有差距；每个数据为什么涨跌；七家对比和我们为什么第一；问题和教训；年度财务目标。
A4: A. 我们的预测 vs 实际
A5: 项目 | B5: 怎么预测的 | C5: 预测 | D5: 实际 | E5: 差距 | F5: 原因
A6: Canyon 销量（千辆） | B6: Concept Test 5U + 推断（当时没有对手的 Utility 车） | C6: 680 | D6: 585 | E6: =D6-C6 -> -95 | F6: 对手同年就上了 3 款 Utility（Axiom $25,999、Elan $28,000、Futura $35,000），Canyon $39,000 最贵；5U 全年 −18%（876K），3U +18.6%（Axiom 第一）。排了 650K，压 65K（41 天）
A7: Cafav 销量（千辆） | B7: Test Market 8.3% × 行业规模 [推断] | C7: 900 | D7: 968 | E7: =D7-C7 -> 68 | F7: 缺货 10–30%，Flex 加满（880 × 1.1）
A8: Crash 销量（千辆） | B8: Test Market 5.1%，再扣掉 Canyon 分走的 5U 买家 [推断] | C8: 450 | D8: 473 | E8: =D8-C8 -> 23 | F8: 缺货 10–30%，Flex 加满（430 × 1.1）
A9: Cameo 销量（千辆） | B9: Test Market 3.3% | C9: 360 | D9: 374 | E9: =D9-C9 -> 14 | F9: 缺货 10–30%，Flex 加满（340 × 1.1）
A10: 销量合计（千辆） | B10: 同上 | C10: 2390 | D10: 2400 | E10: =D10-C10 -> 10 | F10: 三款老车多卖的 105K 抵掉了 Canyon 少卖的 95K
A11: Cafav 份额 | B11: Test Market | C11: 0.083 | D11: 0.091 | E11: =D11-C11 -> 0.008 | F11: 新版第二年，2F、3S、4F 都是第一
A12: Crash 份额 | B12: Test Market | C12: 0.051 | D12: 0.044 | E12: =D12-C12 -> -0.007 | F12: 是产量卡住了（缺货 10–30%），不是没人要
A13: Cameo 份额 | B13: Test Market | C13: 0.033 | D13: 0.035 | E13: =D13-C13 -> 0.002 | F13: 提价 10% 还缺货
A14: 超产能费（$M） | B14: Manufacturing 页面按排产 2,300K 读数 | C14: 96 | D14: 450 | E14: =D14-C14 -> 354 | F14: Flex 给三款老车多产 165K，利用率 109.6%
A15: 营收（$M） | B15: Pro-Forma | C15: 59408 | D15: 58444 | E15: =D15-C15 -> -964 | F15: Canyon 少卖 95K（约 −$3.26B），老车多卖 105K（约 +$2.29B）
A16: COGS（$M） | B16: Pro-Forma | C16: 39318 | D16: 39023 | E16: =D16-C16 -> -295 | F16: Canyon 没卖掉的成本留在库存里；超产能费多 $354M
A17: 毛利率 | B17: Pro-Forma | C17: 0.338 | D17: 0.332 | E17: =D17-C17 -> -0.006 | F17: 超产能费多；单车毛利最高的 Canyon 卖少了
... A21: 库存（千辆） | B21: Pro-Forma | C21: 0 | D21: 65 | E21: =D21-C21 -> 65 | F21: 全是 Canyon（41 天）
A22: Firm Preference | B22: [推断] Canyon 上市 + 营销 $1.1B 会继续升 | C22: 上升 | D22: 0.225 | E22: +3.1 点 | F22: ✅ 一款新车 + 一款升级 + 营销七家最多
A23: 股价（$） | B23: 没有单独预测；今年不增发 | C23: — | D23: 104.63 | E23: +90% | F23: 净利 3 倍多；没增发，股价和市值同比例涨
A24: 三情景 | B24: startup-financial-modeling | C24: 基准 $9,680M；保守 90% 约 $8.4B | D24: 约基准的 95% | E24: — | F24: 落在基准和保守之间
A25: 全行业销量（千辆） | B25: 没有单独预测 | C25: — | D25: 10670 | E25: — | F25: 是系统预测 14,314K 的 75%，“约 77%”的规律还成立
A27: B. 每个数据为什么涨、为什么跌（Year 2 → Year 3）
A28: 项目 | B28: Year 2 | C28: Year 3 | D28: 变化 | E28: 原因
A29: 营收（$M） | B29: 32507 | C29: 58444 | D29: =IFERROR((C29-B29)/B29,"—") -> 0.79788969 | E29: 产能 1,500K → 2,250K，销量 1,682K → 2,400K（+43%）；Canyon 一辆 $34,320（dealer invoice）；老车提价约 10%
A30: COGS（$M） | B30: 24225 | C30: 39023 | D30: =IFERROR((C30-B30)/B30,"—") -> 0.61085655 | E30: 销量增加；Canyon 单车变动成本 $20,015；超产能费 $400M → $450M
A31: 毛利率 | B31: 0.255 | C31: 0.332 | D31: =C31-B31 -> 0.077 | E31: Canyon 单车毛利 $14,305 拉高平均；老车提价
A32: 营销（$M） | B32: 675 | C32: 1105 | D32: =IFERROR((C32-B32)/B32,"—") -> 0.63703704 | E32: Canyon 广告 $200M；企业广告 $150M → $410M
A33: 研发（$M） | B33: 1868 | C33: 2596 | D33: =IFERROR((C33-B33)/B33,"—") -> 0.38972163 | E33: Canyon $560M、Cosmo $488M、第 5 个中心 $643M、Crash $188M、Cameo $174M、技术 $544M
A34: G&A（$M） | B34: 1193 | C34: 1558 | D34: =IFERROR((C34-B34)/B34,"—") -> 0.30595138 | E34: 销量和经销商增加（+48 家开业）；培训费 $30M
A35: 营业利润（$M） | B35: 4546 | C35: 14162 | D35: =IFERROR((C35-B35)/B35,"—") -> 2.1152662 | E35: 毛利多了约 $11.1B，费用只多了约 $1.5B
A36: 利息（$M，负数是收入） | B36: 0 | C36: -60 | D36: — | E36: CD 利息收入 $60M
A37: 净利（$M） | B37: 2945 | C37: 9242 | D37: =IFERROR((C37-B37)/B37,"—") -> 2.1382003 | E37: 上面几项合起来
A38: EPS（$） | B38: 4.09 | C38: 12.84 | D38: =IFERROR((C38-B38)/B38,"—") -> 2.1393643 | E38: 股数没变（720M）
A39: 净利率（ROS） | B39: 0.091 | C39: 0.158 | D39: =C39-B39 -> 0.067 | E39: —
A40: 现金（$M） | B40: 1400 | C40: 2332 | D40: =IFERROR((C40-B40)/B40,"—") -> 0.66571429 | E40: 经营现金流 +9,695；扩产 −5,394、retooling −1,269、买 CD −2,000、分红 −100
A41: 库存（$M） | B41: 0 | C41: 1372 | D41: — | E41: Canyon 65K
A42: 应收账款（$M） | B42: 2560 | C42: 4442 | D42: =IFERROR((C42-B42)/B42,"—") -> 0.73515625 | E42: 销售额增加
A43: 厂房设备（$M） | B43: 17326 | C43: 23989 | D43: =IFERROR((C43-B43)/B43,"—") -> 0.38456655 | E43: 扩产 +800K（Y4 起可用）+ retooling
A44: 负债（$M） | B44: 0 | C44: 0 | D44: — | E44: 没有借钱
A45: 股东权益（$M） | B45: 14351 | C45: 23493 | D45: =IFERROR((C45-B45)/B45,"—") -> 0.63702878 | E45: 净利 $9,242M − 分红 $100M；没增发
A46: ROE | B46: 0.205 | C46: 0.393 | D46: =C46-B46 -> 0.188 | E46: 净利涨 214%，权益只涨 64%
A47: 股价（$） | B47: 55.09 | C47: 104.63 | D47: =IFERROR((C47-B47)/B47,"—") -> 0.89925576 | E47: 净利 3 倍多、负债为 0、份额第一
A48: 市值（$M） | B48: 39664 | C48: 75332 | D48: =IFERROR((C48-B48)/B48,"—") -> 0.89925373 | E48: 全部来自股价上涨（没增发）
A49: Firm Preference | B49: 0.194 | C49: 0.225 | D49: =C49-B49 -> 0.031 | E49: Canyon 上市、Crash 升级、营销七家最多
A50: 销量份额 | B50: 0.177 | C50: 0.225 | D50: =C50-B50 -> 0.048 | E50: 产能 +50% + Canyon
A51: Cafav 销量（千辆） | B51: 792 | C51: 968 | D51: =IFERROR((C51-B51)/B51,"—") -> 0.22222222 | E51: 排 880 + Flex；2F、3S、4F 第一；缺货 10–30%
A52: Cafav 贡献（$M） | B52: 4598 | C52: 7688 | D52: =IFERROR((C52-B52)/B52,"—") -> 0.67203132 | E52: $24,000 → $26,400
A53: Canyon 销量（千辆） | B53: 0 | C53: 585 | D53: — | E53: 上市第一年；5U、5L 第一；压 65K
A54: Canyon 贡献（$M） | B54: 0 | C54: 8109 | D54: — | E54: 单车贡献 $13,860，四款最高
A55: Crash 销量（千辆） | B55: 528 | C55: 473 | D55: =IFERROR((C55-B55)/B55,"—") -> -0.10416667 | E55: 排产减少（430 + Flex）；5U 买家被 Canyon 接走
A56: Crash 贡献（$M） | B56: 4042 | C56: 4062 | D56: =IFERROR((C56-B56)/B56,"—") -> 0.0049480455 | E56: $24,000 → $25,500，贡献持平
A57: Cameo 销量（千辆） | B57: 362 | C57: 374 | D57: =IFERROR((C57-B57)/B57,"—") -> 0.033149171 | E57: 提价 10% 销量还多了
A58: Cameo 贡献（$M） | B58: 1099 | C58: 1557 | D58: =IFERROR((C58-B58)/B58,"—") -> 0.41674249 | E58: $13,900 → $15,290
A59: FCF（$M） | B59: -1753 | C59: 3032 | D59: — | E59: 经营现金流 $9,695M − 扩产和 retooling $6,663M；第一次转正
A61: C. 七家对比（Year 3）和为什么我们第一
A62: 公司 | B62: 净利（$M） | C62: 毛利率 | D62: 营销（$M） | E62: 研发（$M） | F62: 利息（$M） | G62: 股价 | H62: 市值（$M） | I62: 总负债（$M） | J62: 偏好度 | K62: 销量份额 | L62: 库存（千辆） | M62: 今年做了什么
A63: A | B63: 1730 | C63: 0.239 | D63: 225 | E63: 1578 | F63: 385 | G63: 42.78 | H63: 21390 | I63: 5927 | J63: 0.114 | K63: 0.113 | L63: 286 | M63: 推出 Utility 车 Axiom（$25,999，3U 第一）；升级 Ace；86 天库存
A64: B | B64: 3174 | C64: 0.232 | D64: 486 | E64: 606 | F64: 201 | G64: 57.78 | H64: 34625 | I64: 3660 | J64: 0.169 | K64: 0.155 | L64: 0 | M64: 又升级 Buzzy、Boffo、Boss 三款；累计净利第 2
A65: C（我们） | B65: 9242 | C65: 0.332 | D65: 1105 | E65: 2596 | F65: 0 | G65: 104.63 | H65: 75332 | I65: 0 | J65: 0.225 | K65: 0.225 | L65: 65 | M65: Canyon 上市、Crash minor；第 5 个研发中心；扩产 +800K（Y4 起）；买 CD
A66: D | B66: 763 | C66: 0.171 | D66: 217 | E66: 490 | F66: 496 | G66: 22.67 | H66: 11335 | I66: 7734 | J66: 0.056 | K66: 0.11 | L66: 284 | M66: 没有新车或升级；宣布要做 Utility；88 天库存，负债最高
A67: E | B67: 2484 | C67: 0.22 | D67: 570 | E67: 903 | F67: 0 | G67: 50.38 | H67: 30191 | I67: 0 | J67: 0.16 | K67: 0.132 | L67: 62 | M67: 推出 Utility 车 Elan（$28,000）；升级 Efizz、Egad
A68: F | B68: 3399 | C68: 0.26 | D68: 910 | E68: 956 | F68: 110 | G68: 60.02 | H68: 35968 | I68: 2000 | J68: 0.211 | K68: 0.139 | L68: 3 | M68: 推出 Utility 车 Futura（$35,000）；升级 Fantasy、Fast；营销第 2 多
A69: G | B69: 612 | C69: 0.194 | D69: 525 | E69: 1869 | F69: 214 | G69: 32.18 | H69: 19308 | I69: 3882 | J69: 0.065 | K69: 0.126 | L69: 163 | M69: 建新研发中心；今年没有新车或升级；44 天库存
A70: 我们第一的原因 | B70: ① 毛利率 33.2%，比第 2 名 F（26.0%）高 7 点：Canyon 单车毛利 $14,305，三款老车提价 10% 还缺货；② 规模最大：卖 2,400K（第 2 名 B 1,650K）；③ 没有负债，不付利息；④ 偏好度第 1（22.5%）
A71: F 为什么第二 | B71: 一年推出 Futura 又升级 2 款，营销 $910M，偏好度 21.1% 第 2；毛利率 26.0% 第 2；市值 $36.0B 比 B 高，所以总分略高于 B
A72: B | B72: 连续两年一次升级 3 款车（研发只花 $606M），没压库存；累计净利 $7,210M 第 2
A73: A、D、G 的问题 | B73: A、D 压了 86–88 天库存（286K、284K），负债 $5.9B、$7.7B；G 研发 $1,869M 却没有新车或升级，净利只有 $612M
A75: D. 问题和教训
A76: 问题 | B76: 证据 | C76: 下一年怎么改
A77: Canyon 首年排产太多 | B77: 推断 680K、排 650K，实际卖 585K，压 65K（$1.37B 现金）；A、E、F 同年就上了 Utility | C77: 新车首年按推断量的 85–90% 排产；已宣布做同类车的对手，按“当年就会上市”来算
A78: Flex 没有替 Canyon 减产 | B78: 产 650K = 排产，卖 585K | C78: 不靠 Flex 防库存 [推断：至少新车上市当年如此]；Y4 Canyon 排产先扣 65K 库存
A79: 三款老车又定低了 | B79: 提价 6–10% 后仍缺货 10–30% | C79: Y4 用 Test Market 继续往上测价格
A80: 超产到 110% | B80: 超产能费 $450M | C80: Y4 产能 3,050K（+800K 到位），利用率会降
A81: 5U 变挤了 | B81: 对手三款 Utility 在 $26–35K；D 也宣布要做；5U 全年 −18% | C81: Canyon 保持配置领先（Styling 7、Q5）；Y4 Test Market 测 $36–39K
A83: E. 年度财务目标
A84: 目标 | B84: 结果 | C84: 达标
A85: 营收增长 | B85: +79.8% | C85: ✅
A86: 毛利率 ≥ 10%，保持或提高 | B86: 25.5% → 33.2% | C86: ✅
A87: 净利率 ≥ 4.5%，保持或提高 | B87: 9.1% → 15.8% | C87: ✅
A88: FCF 为正 | B88: −$1,753M → +$3,032M（第一次转正） | C88: ✅
A89: ROE ≥ 10%，保持或提高 | B89: 20.5% → 39.3% | C89: ✅
A90: 市值增长 | B90: +90% | C90: ✅

Sheet 正式Y4复盘
A1: 正式 Year 4 结果复盘（10/27 出结果）
A2: 还是七家第 1：Weighted Score 98.2（第 2 名 F 从 79.0 升到 83.6，差距从 19.2 分缩小到 14.6 分）；净利 $15,578M（F $6,401M）；累计净利 $30,284M（F $13,456M）；市值 $112.9B（F $59.0B）；销量份额 24.3%、Firm Preference 25.7%，都是第 1。净利增速从 +214% 降到 +69%，但增加的绝对额差不多（+$6.30B → +$6.34B）。
A4: A. 我们的预测 vs 实际
A5: 项目 | B5: 怎么预测的 | C5: 预测 | D5: 实际 | E5: 差距 | F5: 原因
A6: Cafav 销量（千辆） | B6: 排 1,150K（Test Market 9.1% 再多排 100K） | C6: 1150 | D6: 1094 | E6: =D6-C6 -> -56 | F6: 只卖了 1,094K，压 56K（19 天）；Flex 没有减产
A7: Canyon 销量（千辆） | B7: 排 600K + 库存 65K（担心 D 的 Utility） | C7: 665 | D7: 725 | E7: =D7-C7 -> 60 | F7: Flex 加满到 660K，加上库存全卖光，缺货 >30%；du004 只拿到 5U 的 7.4%
A8: Cosmo 销量（千辆） | B8: Concept Test 44.1% × 估计量的 90% | C8: 245 | D8: 264 | E8: =D8-C8 -> 19 | F8: Flex 加满（240 × 1.1），缺货 >30%；4F 第一（28.1%）
A9: Cameo 销量（千辆） | B9: Concept Test 43.2% | C9: 320 | D9: 330 | E9: =D9-C9 -> 10 | F9: Flex 加满（300 × 1.1），缺货 >30%；2E 第一（27.8%）
A10: Crash 销量（千辆） | B10: 排 520K（Test Market 4.3% 再多排 40K） | C10: 520 | D10: 502 | E10: =D10-C10 -> -18 | F10: 压 18K（13 天）；1T 第一（17.5%）
A11: 销量合计（千辆） | B11: Pro-Forma | C11: 2900 | D11: 2915 | E11: =D11-C11 -> 15 | F11: 缺货的三款多卖 89K，Cafav、Crash 少卖 74K
A12: 营收（$M） | B12: Pro-Forma | C12: 78008 | D12: 79035 | E12: =D12-C12 -> 1027 | F12: 卖得多的是单价高的 Canyon、Cosmo
A13: 毛利率 | B13: Pro-Forma | C13: 0.361 | D13: 0.362 | E13: =D13-C13 -> 0.001 | F13: 基本准
A14: G&A（$M） | B14: Pro-Forma | C14: 1850 | D14: 1857 | E14: =D14-C14 -> 7 | F14: 基本准
A15: 净利（$M） | B15: Pro-Forma | C15: 15262 | D15: 15578 | E15: =D15-C15 -> 316 | F15: 多卖的是单车贡献最高的两款
A16: 期末现金（$M） | B16: Pro-Forma（另有 CD $10,000M） | C16: 9274 | D16: 8564 | E16: =D16-C16 -> -710 | F16: Cafav、Crash 压了 74K 辆库存（$1,158M）
A17: 利用率 | B17: Manufacturing 页面 | C17: 0.92 | D17: 0.959 | E17: =D17-C17 -> 0.039 | F17: Flex 给缺货的三款多产
A18: 全行业销量（千辆） | B18: 系统预测 | C18: 15604 | D18: 11999 | E18: =D18-C18 -> -3605 | F18: 只有预测的 77%，规律还成立
A19: 股价（$） | B19: 没有单独预测 | C19: — | D19: 156.75 | E19: +50% | F19: 净利 +69%
A21: B. 每个数据为什么涨、为什么跌（Year 3 → Year 4）
A22: 项目 | B22: Year 3 | C22: Year 4 | D22: 变化 | E22: 原因
A23: 营收（$M） | B23: 58444 | C23: 79035 | D23: =IFERROR((C23-B23)/B23,"—") -> 0.35232017 | E23: 销量 2,400K → 2,915K（+21%）；单车 dealer invoice $24,351 → $27,111（+11%，提价约 10%）；Cosmo 上市
A24: COGS（$M） | B24: 39023 | C24: 50407 | D24: =IFERROR((C24-B24)/B24,"—") -> 0.29172539 | E24: 销量增加；Cafav、Canyon 降成本；超产能费 $450M → 0
A25: 毛利率 | B25: 0.332 | C25: 0.362 | D25: =C25-B25 -> 0.03 | E25: 提价；Cosmo 单车毛利 $14,275；没有超产能费
A26: 营销（$M） | B26: 1105 | C26: 1555 | D26: =IFERROR((C26-B26)/B26,"—") -> 0.40723982 | E26: Canyon 广告加倍；Cosmo 上市 $260M
A27: 研发（$M） | B27: 2596 | C27: 1596 | D27: =IFERROR((C27-B27)/B27,"—") -> -0.38520801 | E27: 取消 Comet、Cargo、Quality 技术；没有建新中心
A28: G&A（$M） | B28: 1558 | C28: 1857 | D28: =IFERROR((C28-B28)/B28,"—") -> 0.19191271 | E28: 经销商 +52 家；销量增加
A29: 营业利润（$M） | B29: 14162 | C29: 23620 | D29: =IFERROR((C29-B29)/B29,"—") -> 0.66784352 | E29: 毛利多了约 $9.2B，费用只多了约 $0.25B
A30: 利息（$M，负数是收入） | B30: -60 | C30: -350 | D30: — | E30: CD 从 $2B 加到 $10B
A31: 净利（$M） | B31: 9242 | C31: 15578 | D31: =IFERROR((C31-B31)/B31,"—") -> 0.68556589 | E31: 增加 $6.34B，和 Y3 增加的 $6.30B 差不多；增速变慢是因为基数大了
A32: EPS（$） | B32: 12.84 | C32: 21.64 | D32: =IFERROR((C32-B32)/B32,"—") -> 0.68535826 | E32: 股数没变（720M）
A33: 净利率（ROS） | B33: 0.158 | C33: 0.197 | D33: =C33-B33 -> 0.039 | E33: —
A34: 现金（$M） | B34: 2332 | C34: 8564 | D34: =IFERROR((C34-B34)/B34,"—") -> 2.6723842 | E34: 经营现金流 +18,361；扩产 −2,711、retooling −1,319、CD 净买 −8,000、分红 −100
A35: 库存（$M） | B35: 1372 | C35: 1158 | D35: =IFERROR((C35-B35)/B35,"—") -> -0.15597668 | E35: Canyon 65K 卖完；Cafav 56K、Crash 18K
A36: 应收账款（$M） | B36: 4442 | C36: 5532 | D36: =IFERROR((C36-B36)/B36,"—") -> 0.24538496 | E36: 销售额增加
A37: 厂房设备（$M） | B37: 23989 | C37: 28018 | D37: =IFERROR((C37-B37)/B37,"—") -> 0.16795198 | E37: 扩产 +400K（Y5 起可用）+ retooling
A38: 负债（$M） | B38: 0 | C38: 0 | D38: — | E38: 没有借钱
A39: 股东权益（$M） | B39: 23493 | C39: 38972 | D39: =IFERROR((C39-B39)/B39,"—") -> 0.65887711 | E39: 净利 $15,578M − 分红 $100M
A40: ROE | B40: 0.393 | C40: 0.4 | D40: =C40-B40 -> 0.007 | E40: —
A41: 股价（$） | B41: 104.63 | C41: 156.75 | D41: =IFERROR((C41-B41)/B41,"—") -> 0.49813629 | E41: 净利 +69%；负债为 0；份额、偏好度第一
A42: 市值（$M） | B42: 75332 | C42: 112857 | D42: =IFERROR((C42-B42)/B42,"—") -> 0.49812829 | E42: 全部来自股价上涨
A43: Firm Preference | B43: 0.225 | C43: 0.257 | D43: =C43-B43 -> 0.032 | E43: Cosmo 上市；Cameo、Cafav、Canyon 升级或降成本
A44: 销量份额 | B44: 0.225 | C44: 0.243 | D44: =C44-B44 -> 0.018 | E44: 产能 +800K
A45: Cafav 贡献（$M） | B45: 7688 | C45: 11383 | D45: =IFERROR((C45-B45)/B45,"—") -> 0.48061915 | E45: $26,400 → $29,000，单车 $10,405
A46: Canyon 贡献（$M） | B46: 8109 | C46: 9864 | D46: =IFERROR((C46-B46)/B46,"—") -> 0.21642619 | E46: 725K，单车 $13,607
A47: Cosmo 贡献（$M） | B47: 0 | C47: 3509 | D47: — | E47: 上市第一年，单车 $13,291
A48: Crash 贡献（$M） | B48: 4062 | C48: 4867 | D48: =IFERROR((C48-B48)/B48,"—") -> 0.19817824 | E48: $25,500 → $27,000
A49: Cameo 贡献（$M） | B49: 1557 | C49: 1007 | D49: =IFERROR((C49-B49)/B49,"—") -> -0.35324342 | E49: 新版尺寸 22 转向 2E；单车 $3,051（Y3 $4,164）
A50: FCF（$M） | B50: 3032 | C50: 14331 | D50: =IFERROR((C50-B50)/B50,"—") -> 3.7265831 | E50: 经营现金流 $18,361M − 扩产和 retooling $4,030M
A52: C. 七家对比（Year 4）和为什么我们第一
A53: 公司 | B53: 净利（$M） | C53: 毛利率 | D53: 营销（$M） | E53: 研发（$M） | F53: 累计净利（$M） | G53: 股价 | H53: 市值（$M） | I53: 总负债（$M） | J53: 偏好度 | K53: 销量份额 | L53: Weighted Score | M53: 今年做了什么
A54: A | B54: 2404 | C54: 0.213 | D54: 230 | E54: 1209 | F54: 7418 | G54: 57.16 | H54: 30050 | I54: 4927 | J54: 0.104 | K54: 0.128 | L54: 63.3 | M54: 升级 Alfa（Safety 6 / Quality 6，$23,998）和 Ace
A55: B | B55: 3650 | C55: 0.237 | D55: 486 | E55: 599 | F55: 10860 | G55: 66.32 | H55: 39743 | I55: 2660 | J55: 0.137 | K55: 0.144 | L55: 74.8 | M55: 又升级 Buzzy、Boffo、Boss；第 3
A56: C（我们） | B56: 15578 | C56: 0.362 | D56: 1555 | E56: 1596 | F56: 30284 | G56: 156.75 | H56: 112857 | I56: 0 | J56: 0.257 | K56: 0.243 | L56: 98.2 | M56: Cosmo、新 Cameo 上市；Canyon、Cafav 降成本；Chow 开工；扩产 +400K
A57: D | B57: 292 | C57: 0.162 | D57: 575 | E57: 985 | F57: 4579 | G57: 18.99 | H57: 9495 | I57: 3377 | J57: 0.129 | K57: 0.096 | L57: 51.8 | M57: 推出 Utility 车 du004（$30,000）；升级 Delite、Defy
A58: E | B58: 3138 | C58: 0.232 | D58: 600 | E58: 776 | F58: 9318 | G58: 59.05 | H58: 35386 | I58: 0 | J58: 0.11 | K58: 0.125 | L58: 69.3 | M58: 升级 Efizz、Elan
A59: F | B59: 6401 | C59: 0.302 | D59: 810 | E59: 827 | F59: 13456 | G59: 84.33 | H59: 58966 | I59: 2000 | J59: 0.18 | K59: 0.15 | L59: 83.6 | M59: 升级 Fantasy、Fast、Futura；净利 +88%
A60: G | B60: 550 | C60: 0.167 | D60: 705 | E60: 1210 | F60: 6244 | G60: 28.6 | H60: 17160 | I60: 3481 | J60: 0.082 | K60: 0.115 | L60: 56.6 | M60: 推出家用车 Gala（$24,000）；升级 Gone；宣布做 Minivan
A61: 我们第一的原因 | B61: ① 毛利率 36.2%，比第 2 名 F（30.2%）高 6 点；② 规模最大：营收 $79.0B，是 F 的 1.9 倍；③ 没有负债；④ 偏好度和份额都第 1
A62: F 为什么追得快 | B62: 一年升级 3 款（含 Utility 车 Futura，5U 份额 20.0%），毛利率 30.2%；净利 +88%，市值 +64%，比我们的 +50% 快
A63: 增速为什么变慢 | B63: ① 基数变大：净利增加的绝对额和 Y3 一样（约 $6.3B）；② Y3 的跳升来自 Canyon 上市（新增贡献 $8.1B），Y4 的新车 Cosmo 只有 $3.5B；③ 产能是瓶颈：利用率 95.9%，Canyon、Cosmo、Cameo 缺货 >30%；④ 产能分错了车：多排的给了 Cafav、Crash，结果压了 74K 辆
A65: D. 问题和教训
A66: 问题 | B66: 证据 | C66: 下一年怎么改
A67: 产能分给了错的车 | B67: Cafav 多排 100K、Crash 多排 40K，压了 74K；Canyon（单车 $13,607）、Cosmo（$13,291）缺货 >30% | C67: 按单车贡献分配产能（老师的 Manufacturing priority）；多排给缺货的高毛利车
A68: Canyon 被对手吓到少排 | B68: 为了 D 的 Utility 只排 600K；du004 只拿到 5U 的 7.4%，Canyon 41.7% 第一 | C68: D5 Canyon 排 820K
A69: Test Market 低估缺货车的需求 | B69: baseline 份额就是上一年被产量卡住的份额 | C69: 缺货 >30% 的车，排产要比 Test Market 多
A70: Flex 不减产 | B70: Cafav 产 1,150 = 排产，压 56K（Y3 的 Canyon 也一样） | C70: 不靠 Flex 防库存
A71: 对手追上 Cafav | B71: Alfa 升到 Safety 6 / Quality 6，Cafav 在 2F 的 hot button 只剩 avg，份额 22.3% → 19.6% | C71: D5 Cafav minor（Safety 6 / Quality 5）；买 Safety 技术，Y6 到 Safety 7
A73: E. 年度财务目标
A74: 目标 | B74: 结果 | C74: 达标
A75: 营收增长 | B75: +35.2% | C75: ✅
A76: 毛利率 ≥ 10%，保持或提高 | B76: 33.2% → 36.2% | C76: ✅
A77: 净利率 ≥ 4.5%，保持或提高 | B77: 15.8% → 19.7% | C77: ✅
A78: FCF 为正 | B78: $3,032M → $14,331M | C78: ✅
A79: ROE ≥ 10%，保持或提高 | B79: 39.3% → 40.0% | C79: ✅
A80: 市值增长 | B80: +49.8% | C80: ✅

Sheet 结论总表
A1: 试错结论总表：哪些对、哪些不好、哪些还要验证
A2: ✅ 已验证有效 ❌ 不好 ⏳ 没有结论 ⬜ 练习轮测不了，正式比赛一开始就要做（Y4 结果已于 10/6 更新） 第 49 行起是正式比赛 Year 1（10/11）的新结论。
A4: 状态 | B4: 类别 | C4: 做法 | D4: 证据（数据） | E4: 正式比赛怎么做 | F4: 验证时间
A5: ✅ | B5: 产能 | C5: 提前一年扩产 | D5: 超产能费 $1,544M（Y1）→ $141M（Y2）→ 0（Y3） | E5: 预计会持续超产就提前一年扩产 | F5: Y2–Y3
A6: ✅ | B6: 测试 | C6: Test Market 的份额预测 | D6: Y2 Crash 预测 4.4%，实际 4.3%；Y3 Cafav 预测 6.6%，实际 6.6%，Cameo 预测 3.0%，实际 2.8% | E6: 已经在卖的车，定价和排产前必测 | F6: Y2–Y3
A7: ✅ | B7: 生产 | C7: 排产公式：份额 × 全行业实际销量 | D7: Cafav 6.6% × 10,339K ≈ 682K，实际 686K | E7: 用这个公式排产，不要用预测的需求 | F7: Y3
A8: ✅ | B8: 测试 | C8: 新车用 Concept Test 定价 | D8: Canyon 测出对价格不敏感；定 $31K 后仍缺货超过 30% | E8: 新车或新版上市前用 Concept Test 测价格区间 | F8: Y3
A9: ✅ | B9: 定价 | C9: 提价 + 加营销，不靠降价 | D9: Y3 Crash $23K + 营销 → +$500M，降价 → −$134M；Y4 Crash 降价 → −$84M | E9: 需求大于供给时提价，同时加营销 | F9: Y3–Y4
A10: ✅ | B10: 融资 | C10: 用增发代替债务 | D10: Y3 增发 $2.5B 后股价 +69%，市值升到第 1 | E10: 开局就用增发还掉 7.5% 的短贷，不发债 | F10: Y3
A11: ✅ | B11: 营销 | C11: 营销占营收约 2% | D11: Firm Preference 10.8% → 20.4%，第 1 | E11: 营销至少占营收 2% | F11: Y3
A12: ✅ | B12: 产品 | C12: 先对准尺寸 | D12: Fantasy 尺寸 40，2F 第 1；Cafav 38 → 40 + Safety 5，Likely to buy 14.2% → 24.3% | E12: 先把尺寸做到偏好区间中间，再改 ISSQ | F12: Y2–Y4
A13: ✅ | B13: 产品 | C13: 抢先进入没人做的细分市场 | D13: Canyon 在 5U 份额 47.3%，单车贡献约 $7,300（Y3） | E13: 第 1 年就开始开发新类别的车 | F13: Y3
A14: ✅ | B14: Skill | C14: pricing skill 复查定价 | D14: 发现 Codex 给 Canyon 定的 $24,900 扣掉折扣后低于成本 | E14: 每年定价后用 pricing skill 复查 | F14: Y3
A15: ✅ | B15: Skill | C15: startup-financial-modeling 做三情景现金检查 | D15: 算出销量低于计划约 85% 时才会触发自动借贷 | E15: 排产和现金都按保守情景检查 | F15: Y4
... A93: ⏳ | B93: 营销 | C93: 营销 $1,753M → $2,213M（营收 2.5%）：企业广告 $900M、Cafav 250 / 150、Crash 130 / 50；缺货的三款不加 | D93: Cafav $30K 被评 worst（Concept Test 5.4%），衰退 + 油价 $4.90，Cafav、Crash 有压库存风险；课程把营销占营收 2–4% 列为市值因素；Test Market 用完了没测 | E93: 看 Y5 偏好度、Cafav 和 Crash 的库存、市值 | F93: 正式 Y5
A95: 统计 | C95: ✅ 有效 | D95: =COUNTIF(A5:A93,"✅") -> 48
C96: ❌ 不好 | D96: =COUNTIF(A5:A93,"❌") -> 25
C97: ⏳ 待验证 | D97: =COUNTIF(A5:A93,"⏳") -> 12
C98: ⬜ 正式比赛再验证 | D98: =COUNTIF(A5:A93,"⬜") -> 4

Sheet 操作流程
A1: 每一年的操作流程（我们实际在用的做法）
A2: 按顺序做。第 3、5、6、10、11、13 步是试错之后加进来的规则。
A4: 步骤 | B4: 做什么 | C4: 在系统 / 工具的哪里 | D4: 我们的规则和注意事项
A5: 1 | B5: 确认没有别的程序在改决策 | C5: Decision Log | D5: Codex 自动任务已经停了；开始前和截止前都看一眼 Decision Log
A6: 2 | B6: 看上一年的结果 | C6: Company：Dashboard、Products、Manufacturing、Income、Cash Flow；Competition：Financials | D6: 重点看 shortage 提示、库存天数、现金、有没有被系统自动借贷
A7: 3 | B7: 买必买的报告 | C7: Market → Microsegments；Tools → Focus Groups | D7: 只买自己的细分市场（今年是 1E、2E、2F、3T、5U）
A8: 4 | B8: 安排研发 | C8: Decisions → Product Development | D8: 每个中心都要放项目；先对准尺寸，尺寸差得多就做 major；minor 会处理掉旧库存；每年只能新建 1 个中心
A9: 5 | B9: 测新车或新版 | C9: Tools → Concept Test | D9: 用来筛选配置和价格区间；不算钱，不能单独用来定价
A10: 6 | B10: 测已经在卖的车 | C10: Tools → Test Market | D10: 定价格和营销预算；看“贡献变化”；促销最多填 baseline 的 2 倍；价格只能在去年的 ±10% 内测
A11: 7 | B11: 排产 | C11: Decisions → Manufacturing | D11: 产量 = Test Market 份额 × 全行业实际销量；不超过产能 10%；要升级的车，前一年少排产；增产要付 retooling 费
A12: 8 | B12: 营销和渠道 | C12: Decisions → Marketing / Distribution | D12: 营销至少占营收 2%；新车上市那年多投；对价格敏感的细分市场多给促销
A13: 9 | B13: 融资 | C13: Decisions → Financing | D13: 按保守情景算现金缺口；不够就增发（上限是市值的 20%）；有债可赎回就赎回；现金宽裕才买 CD
A14: 10 | B14: Pro-Forma + 三情景检查 | C14: Decisions → Pro-Forma；startup-financial-modeling skill | D14: Pro-Forma 是按全部卖光算的；要看销量 90% 和 80% 时现金够不够
A15: 11 | B15: 用 skill 复查定价 | C15: pricing skill | D15: 价格要在“次优替代品”和“客户感知价值”之间，成本只是底线
A16: 12 | B16: 核对 | C16: Decision Summary + Decision Alerts | D16: 逐项对一遍；Alerts 要显示没有警告
... A19: 15 | B19: 截止前最后确认 | C19: Decision Log + Decision Summary | D19: 确认没有被覆盖；期数视图切回当前年份

Sheet Skill和测试工具
A1: 用过的 Skill 和系统里的测试工具：用来干什么、发现了什么、靠不靠谱
A2: Skill 是 Claude 这边的工具；测试工具是 StratSim 系统里要花钱买的调研。
A4: 名称 | B4: 什么时候用 | C4: 用来干什么 | D4: 实际发现了什么 | E4: 评价
A5: pricing（skill） | B5: Y3 定价后复查；正式 Y1 复查定价 | C5: 价值定价：价格定在次优替代品和客户感知价值之间 | D5: 发现 Canyon $24,900 扣掉折扣后低于成本 → 改价后测试，定 $31K 仍缺货；正式 Y1：确认 Cafav $22,385 + 广告加倍是产能受限时贡献最高的组合 | E5: ✅ 有用，每年复查一次
A6: startup-financial-modeling（skill） | B6: Y4 复查现金和融资；正式 Y1 三情景 | C6: 三情景（保守 / 基准 / 乐观）、稀释、Pro-Forma 的乐观偏差 | D6: 销量只有计划的 80% 时会触发借贷；增发稀释约 20%，利息却要明年才省下来；正式 Y1：卖出 90% 现金约 $1.0B，卖出 80% 会被借约 $0.9B（也是 7.5%） | E6: ✅ 有用，每年做一次三情景
A7: humanizer（skill） | B7: 每次写 Rationale | C7: 去掉 AI 写作痕迹，不加数据里没有的事实 | D7: Y3、Y4 的 Rationale 都润色后保存了；正式 Y1 也润色后保存了 | E7: ✅ 规则：必用
A8: xlsx（skill） | B8: 做这份对照表 | C8: 带公式的表格，重新计算后检查有没有错误 | D8: 公式全部算过，0 错误 | E8: ✅
A9: Test Market（系统） | B9: 已经在卖的车 | C9: 份额和贡献变化（只能在去年价格的 ±10% 内测） | D9: 份额误差 ≤ 0.4 个百分点；推翻了 Y4 Crash 降价；正式 Y1：广告加倍时份额 +0.5–0.8 个百分点（待结果验证） | E9: ✅ 最可靠，定价以它为准
A10: Concept Test（系统） | B10: 新车、新版本 | C10: Likely to buy + 每项属性的评价 | D10: Canyon 对价格不敏感；Cafav 改大后 2E 只有 0.3%；Crash 210 HP 被评为 poor MPG；正式 Y1：用来选 Canyon 的 HP（245），并测出 Cafav 新版 $21K 附近的断崖 | E10: ✅ 用来筛选，不能单独定价
A11: Focus Group（系统） | B11: 每年必买 | C11: 每项属性被评为 best / good / too small 等 | D11: 尺寸太小或太大一眼就能看出来 | E11: ✅ 必买
A12: Microsegment（系统） | B12: 每年必买 | C12: 偏好区间、需求预测、价格敏感度 | D12: 需求预测偏高（实际只有预测的 76–85%） | E12: ⚠️ 偏好可以信，需求预测不能直接用
A13: Sales by Microsegment（系统） | B13: 需要时 | C13: 每辆车实际卖到了哪些细分市场 | D13: Cafav 有 20% 卖进 2E；Crash 只有 20% 卖进 3T | E13: ✅ 判断目标市场时很有用
A14: Pro-Forma（系统） | B14: 每年 | C14: 按当前决策预测利润表和现金 | D14: Y2、Y3 净利都比实际高估约 $700M；Y3 现金高估约 $3.3B | E14: ⚠️ 只当参考，要配合三情景
A15: Codex 自动任务 | B15: Y3 初 | C15: 按小时自动填决策 | D15: Canyon 定价低于成本、Crash 尺寸改反、没买 Focus Group | E15: ❌ 已停
A17: 每一期有没有按规则跑 skill（规则 10/3 才定，所以练习轮前两年都没跑）
A18: 期 | B18: pricing | C18: startup-financial-modeling | D18: humanizer | E18: 记录在哪
A19: 练习 Y1 | B19: ❌ | C19: ❌ | D19: ❌ | E19: 当时还没有这条规则
A20: 练习 Y2 | B20: ❌ | C20: ❌ | D20: ❌ | E20: 同上
A21: 练习 Y3 | B21: ✅ | C21: ❌（只看了一种情景，后来被强制借了 $751M） | D21: ✅ | E21: md 第 2 节
A22: 练习 Y4 | B22: ✅ | C22: ✅ | D22: ✅ | E22: md 第 2 节“Y4 决策的 skill 复查”
A23: 正式 Y1 | B23: ✅ | C23: ✅ | D23: ✅ | E23: md 0c 节“正式 Y1 的 skill 复查”；下面这张表
A24: 正式 Y2 | B24: ✅ | C24: ✅ | D24: ✅ | E24: md 0c 节“正式 Y2 的 skill 复查”；下面的 Y2 表
A25: 正式 Y1 pricing 复查：各方案在产能受限时的贡献（销量 = Test Market 份额 × 全行业销量）
A26: 全行业销量（千辆）[推断] | B26: 10100
A27: 车 | B27: 方案 | C27: 价格 | D27: 份额 | E27: 经销商折扣 | F27: 单车变动成本 | G27: 广告 + 促销（$M） | H27: 销量（千辆） | I27: 单车毛利 | J27: 贡献（$M） | K27: 选了吗
A28: Cafav | B28: 原价 / 50 / 35 | C28: 20350 | D28: 0.069 | E28: 0.12 | F28: 13568 | G28: 85 | H28: =D28*$B$26 -> 696.9 | I28: =C28*(1-E28)-F28 -> 4340 | J28: =H28*I28/1000-G28 -> 2939.546
A29: Cafav | B29: $21,000 / 50 / 35 | C29: 21000 | D29: 0.057 | E29: 0.12 | F29: 13568 | G29: 85 | H29: =D29*$B$26 -> 575.7 | I29: =C29*(1-E29)-F29 -> 4912 | J29: =H29*I29/1000-G29 -> 2742.8384
A30: Cafav | B30: $21,800 / 50 / 35 | C30: 21800 | D30: 0.048 | E30: 0.12 | F30: 13568 | G30: 85 | H30: =D30*$B$26 -> 484.8 | I30: =C30*(1-E30)-F30 -> 5616 | J30: =H30*I30/1000-G30 -> 2637.6368
A31: Cafav | B31: $22,385 / 50 / 35 | C31: 22385 | D31: 0.045 | E31: 0.12 | F31: 13568 | G31: 85 | H31: =D31*$B$26 -> 454.5 | I31: =C31*(1-E31)-F31 -> 6130.8 | J31: =H31*I31/1000-G31 -> 2701.4486
A32: Cafav | B32: $21,800 / 100 / 70 | C32: 21800 | D32: 0.055 | E32: 0.12 | F32: 13568 | G32: 170 | H32: =D32*$B$26 -> 555.5 | I32: =C32*(1-E32)-F32 -> 5616 | J32: =H32*I32/1000-G32 -> 2949.688
A33: Cafav | B33: $22,385 / 100 / 70 | C33: 22385 | D33: 0.053 | E33: 0.12 | F33: 13568 | G33: 170 | H33: =D33*$B$26 -> 535.3 | I33: =C33*(1-E33)-F33 -> 6130.8 | J33: =H33*I33/1000-G33 -> 3111.8172 | K33: ✅
A34: Crash | B34: 原价 / 25 / 10 | C34: 20498 | D34: 0.044 | E34: 0.12 | F34: 12982 | G34: 35 | H34: =D34*$B$26 -> 444.4 | I34: =C34*(1-E34)-F34 -> 5056.24 | J34: =H34*I34/1000-G34 -> 2211.9931
A35: Crash | B35: $21,500 / 25 / 10 | C35: 21500 | D35: 0.038 | E35: 0.12 | F35: 12982 | G35: 35 | H35: =D35*$B$26 -> 383.8 | I35: =C35*(1-E35)-F35 -> 5938 | J35: =H35*I35/1000-G35 -> 2244.0044
A36: Crash | B36: $22,500 / 25 / 10 | C36: 22500 | D36: 0.036 | E36: 0.12 | F36: 12982 | G36: 35 | H36: =D36*$B$26 -> 363.6 | I36: =C36*(1-E36)-F36 -> 6818 | J36: =H36*I36/1000-G36 -> 2444.0248
A37: Crash | B37: $22,500 / 50 / 20 | C37: 22500 | D37: 0.041 | E37: 0.12 | F37: 12982 | G37: 70 | H37: =D37*$B$26 -> 414.1 | I37: =C37*(1-E37)-F37 -> 6818 | J37: =H37*I37/1000-G37 -> 2753.3338 | K37: ✅
A38: Cameo | B38: 原价 / 30 / 15 | C38: 11492 | D38: 0.03 | E38: 0.08 | F38: 9571 | G38: 45 | H38: =D38*$B$26 -> 303 | I38: =C38*(1-E38)-F38 -> 1001.64 | J38: =H38*I38/1000-G38 -> 258.49692
A39: Cameo | B39: $12,200 / 30 / 15 | C39: 12200 | D39: 0.029 | E39: 0.08 | F39: 9571 | G39: 45 | H39: =D39*$B$26 -> 292.9 | I39: =C39*(1-E39)-F39 -> 1653 | J39: =H39*I39/1000-G39 -> 439.1637
A40: Cameo | B40: $12,640 / 30 / 15 | C40: 12640 | D40: 0.029 | E40: 0.08 | F40: 9571 | G40: 45 | H40: =D40*$B$26 -> 292.9 | I40: =C40*(1-E40)-F40 -> 2057.8 | J40: =H40*I40/1000-G40 -> 557.72962 | K40: ✅
A42: 结论 | B42: Cafav $22,385 + 广告加倍贡献最高，而且少卖约 160K 辆、省下超产能费；Crash $22,500 + 50/20 最好；Cameo 提价 10% 份额只少 0.1 个百分点，Y2 接着往上测。假设对手不改价；单车变动成本取自 Pro-Forma。
A44: 正式 Y2 pricing 复查：份额 = Test Market 旧版份额 + 升级带来的提升 [推断：Cafav +1.2 点、Crash +0.5 点]
A45: 全行业销量（千辆）[推断] | B45: 10500
A46: 车 | B46: 方案 | C46: 价格 | D46: 份额 | E46: 经销商折扣 | F46: 单车变动成本 | G46: 广告 + 促销（$M） | H46: 销量（千辆） | I46: 单车毛利 | J46: 贡献（$M） | K46: 选了吗
A47: Cafav | B47: $23,000 / 100 / 70 | C47: 23000 | D47: 0.069 | E47: 0.12 | F47: 14885 | G47: 170 | H47: =D47*$B$45 -> 724.5 | I47: =C47*(1-E47)-F47 -> 5355 | J47: =H47*I47/1000-G47 -> 3709.6975
A48: Cafav | B48: $23,500 / 200 / 140 | C48: 23500 | D48: 0.0705 | E48: 0.12 | F48: 14885 | G48: 340 | H48: =D48*$B$45 -> 740.25 | I48: =C48*(1-E48)-F48 -> 5795 | J48: =H48*I48/1000-G48 -> 3949.7488
A49: Cafav | B49: $24,000 / 100 / 70 | C49: 24000 | D49: 0.064 | E49: 0.12 | F49: 14885 | G49: 170 | H49: =D49*$B$45 -> 672 | I49: =C49*(1-E49)-F49 -> 6235 | J49: =H49*I49/1000-G49 -> 4019.92
A50: Cafav | B50: $24,000 / 200 / 140 | C50: 24000 | D50: 0.068 | E50: 0.12 | F50: 14885 | G50: 340 | H50: =D50*$B$45 -> 714 | I50: =C50*(1-E50)-F50 -> 6235 | J50: =H50*I50/1000-G50 -> 4111.79 | K50: ✅
A51: Cafav | B51: $24,600 / 100 / 70 | C51: 24600 | D51: 0.061 | E51: 0.12 | F51: 14885 | G51: 170 | H51: =D51*$B$45 -> 640.5 | I51: =C51*(1-E51)-F51 -> 6763 | J51: =H51*I51/1000-G51 -> 4161.7015
A52: Crash | B52: $23,500 / 50 / 20 | C52: 23500 | D52: 0.046 | E52: 0.12 | F52: 13200 | G52: 70 | H52: =D52*$B$45 -> 483 | I52: =C52*(1-E52)-F52 -> 7480 | J52: =H52*I52/1000-G52 -> 3542.84
A53: Crash | B53: $24,000 / 100 / 40 | C53: 24000 | D53: 0.049 | E53: 0.12 | F53: 13200 | G53: 140 | H53: =D53*$B$45 -> 514.5 | I53: =C53*(1-E53)-F53 -> 7920 | J53: =H53*I53/1000-G53 -> 3934.84 | K53: ✅
A54: Crash | B54: $24,500 / 100 / 40 | C54: 24500 | D54: 0.047 | E54: 0.12 | F54: 13200 | G54: 140 | H54: =D54*$B$45 -> 493.5 | I54: =C54*(1-E54)-F54 -> 8360 | J54: =H54*I54/1000-G54 -> 3985.66
A55: Crash | B55: $24,500 / 50 / 20 | C55: 24500 | D55: 0.042 | E55: 0.12 | F55: 13200 | G55: 70 | H55: =D55*$B$45 -> 441 | I55: =C55*(1-E55)-F55 -> 8360 | J55: =H55*I55/1000-G55 -> 3616.76
A56: Cameo | B56: $13,400 / 30 / 15 | C56: 13400 | D56: 0.033 | E56: 0.08 | F56: 9628 | G56: 45 | H56: =D56*$B$45 -> 346.5 | I56: =C56*(1-E56)-F56 -> 2700 | J56: =H56*I56/1000-G56 -> 890.55
A57: Cameo | B57: $13,900 / 30 / 15 | C57: 13900 | D57: 0.033 | E57: 0.08 | F57: 9628 | G57: 45 | H57: =D57*$B$45 -> 346.5 | I57: =C57*(1-E57)-F57 -> 3160 | J57: =H57*I57/1000-G57 -> 1049.94 | K57: ✅
A59: 结论 | B59: Cafav 从 $23,500 改成 $24,000（贡献 +$162M、少用 26K 产能），没上 $24,600 是因为 Concept Test 在 $24,500 掉到 12%；Crash 选和 Dusty 同价的 $24,000；Cameo 用上限 $13,900。Concept Test 是问卷，定价以 Test Market 为准。
A61: 正式 Y3：skill 都跑过（pricing、startup-financial-modeling、humanizer）；四款车的最终组合都原样测过
A62: 车 | B62: 最终价格 / 广告 / 促销 | C62: 用什么测的 | D62: 测试结果 | E62: 复查结论
A63: Cafav | B63: $26,400 / 150 / 100 | C63: Test Market（原样） | D63: 份额 8.3% 不变，贡献 $6,879M → $8,869M | E63: 提价 10% 份额不变，[推断] 被 Y2 产量卡住
A64: Canyon | B64: $39,000 / 200 / 60 | C64: Concept Test（$39K 原样测过） | D64: 5U：$36K 75.0%、$38K 74.4%、$39K 72.5% | E64: 从 $38,000 提到 $39,000，680K 辆多赚约 $6 亿
A65: Crash | B65: $25,500 / 100 / 40 | C65: Test Market（原样） | D65: 份额 5.5% → 5.1%，贡献 +$205M | E65: Test Market 不知道 Canyon 会分走 5U 买家，排产按约 450K
A66: Cameo | B66: $15,290 / 30 / 15 | C66: Test Market（原样） | D66: 份额 3.8% → 3.3%，贡献 +$224M | E66: 提价腾出产能给高毛利车
A68: 正式 Y4：skill 都跑过（pricing、startup-financial-modeling、humanizer）；Test Market 10 次、Concept Test 9 次，最终组合都原样测过。10/25 按文档复查后取消 Comet、Cargo 和 Quality 技术，改做 Cafav、Crash 降成本；三情景重算，Rationale 重写后再按 humanizer 规则润色
A69: 车 | B69: 最终价格 / 广告 / 促销 | C69: 用什么测的 | D69: 测试结果 | E69: 复查结论
A70: Cafav | B70: $29,000 / 150 / 100 | C70: Test Market（原样） | D70: $27.5K、$28.5K、$29K 份额都是 9.1%；贡献 +$2,517M | E70: 提价信号（缺货、份额不变）；Test Market 只能测到 +10%，上限没测出
A71: Crash | B71: $27,000 / 100 / 40 | C71: Test Market（原样） | D71: $26.5K 4.4%、$27K 4.3%、$27.5K 4.1%；贡献 +$547M | E71: 取中间价
A72: Canyon | B72: $39,000 / 300 / 120 | C72: Test Market（原样） | D72: $37K 5.8%（−$563M）、$41K 3.6%（−$3,222M）；广告 300 / 120 份额 6.4%（+$1,740M） | E72: 唯一测出价格上限的车：不提价、加广告（知名度只有 22.3%）
A73: Cosmo | B73: $40,000 / 200 / 60 | C73: Concept Test（原样） | D73: 4F：I4 / Sf5 $36K 43.8%；I5 / Sf6 $36K 52.1%、$38K 46.7%、$40K 44.1%（价格 poor） | E73: 加 Interior、Safety；按每个买家的贡献：$40K（$14,249 × 44.1% = $6,284）> $38K（$12,489 × 46.7% = $5,832），10/25 用最后一次 Concept Test 后提到 $40K
A74: Cameo（新版） | B74: $16,500 / 50 / 25 | C74: Concept Test（原样） | D74: 2E：Sf3 / Q3 $16K 36.8%；Sf4 / Q4 $16K 46.3%、$16.5K 43.2% | E74: 加 Safety、Quality；2E 对价格敏感，只提 $500
A75: Comet（新车，Y5） | B75: — | C75: Concept Test | D75: 3U $26K 61.4%，属性除价格外全 best | E75: 10/25 复查：取消。3U 价格上限 $26K（已顶格，价格 worst），扣 12% 折扣净收 $22,880，Base Cost $22,055；和 ❌#15、Y5 补充测试冲突
A76: Cargo（新车，Y5） | B76: — | C76: Concept Test | D76: 1T：Cargo 88 / 270 $25K 43.7%；Crash major 78 / 215 只有 18.0% | E76: 10/25 复查：取消。1T 价格敏感度 High；Crash 在 1T 占 16.1%（约 184K 辆，单车 $9,912），Cargo 会抢自己；尺寸 90 练习轮被评 small
A77: 三情景 | B77: — | C77: startup-financial-modeling | D77: 最终版（含 Chow）：乐观约 $16.6B；基准 $15,262M；保守 90% 约 $13.2B（现金约 $3.4B）；很差 80% 约 $11.2B（现金约 −$3.3B，会借短贷）。之前几版的基准：$13,474M → $14,440M → $15,502M | E77: 都赚钱，风险可接受；买 $10B CD
A78: 降成本（中心 1、3） | B78: — | C78: 研发页面 + Pro-Forma + Focus Group | D78: Canyon $20,447 → $20,134、Cafav $15,186 → $14,887，各 $192M；Crash 的降成本（$13,790 → $13,556）10/25 晚换成 Chow | E78: Cafav 在 2F、Crash 在 3T 除价格外全 best，升级加不了份额；不违反 ❌#7（#7 是属性全被评 worst 时还去降成本）
A79: 排产（Cafav、Crash） | B79: 1,150K / 520K（原 1,050K / 480K） | C79: Y3 实际缺货 + 老师 C2 视频 + Pro-Forma | D79: Y3 三款老车 Flex 加满仍缺货 10–30%；Test Market 的 baseline 份额就是被产量卡住的 Y3 份额；retooling 多 $220M；净利 $14,440M → $15,502M | E79: 缺货就是没赚到的钱，空余产能直接多排；Canyon 不加（D 的 Utility 今年上市）
A80: Chow（跑车，Y6） | B80: $34K（计划） | C80: pricing + startup-financial-modeling（重新调用）+ 研发页面概念车 | D80: 3S：540K、想要 Sports、$24–36K；Base Cost $22,341、开发 $1,318M；每辆约 $7,600。Y6 税后：保守约 −$0.8B、基准约 −$0.3B、乐观约打平。4S 超跑（$25,208、$1,472M）基准约 −$0.55B | E80: 只看净利小亏，赌市值（产品组合）和 BoD 故事；D5 用 Concept Test 测，数字不好就砍，最多亏约 $0.24B
A82: 正式 Y5：skill 都用过（pricing、startup-financial-modeling 在 10/25 为 Chow 重新调用后照同样方法复查，humanizer 10/27 重新调用）；Concept Test 10 次、Test Market 10 次，最终组合都原样测过
A83: 车 | B83: 最终价格 / 广告 / 促销 | C83: 用什么测的 | D83: 测试结果 | E83: 复查结论
A84: Cafav | B84: $30,000 / 150 / 100 | C84: Test Market（升级前的车）+ Concept Test（升级版） | D84: TM $30K：9.1% → 8.6%，+$68M；CT 升级版 2F $29K 6.2%、$31K 4.2%（Safety best、Quality avg） | E84: 2F 价格敏感度高、区间 $20–30K；靠升级撑住提价
A85: Cameo | B85: $18,150 / 35 / 18 | C85: Test Market（原样） | D85: $18,150：2.8% → 2.7%，+$545M；少投广告 +$567M | E85: 缺货 >30%，提 10%
A86: Canyon | B86: $40,000 / 300 / 120 | C86: Test Market（原样） | D86: $42,900：6.0% → 4.3%（−$1,952M）；$40K 6.0%（+$725M）；$40K / 200 / 80 6.0%（+$865M，知名度 41.0% → 37.6%） | E86: 已高于 5U 区间（$26–38K），只提 $1,000；保住知名度
A87: Cosmo | B87: $44,000 / 200 / 60 | C87: Test Market（原样） | D87: $44K：2.2% 不变，+$1,056M；150 / 45 +$1,121M（知名度 19.3% → 16.8%） | E87: 4F 价格敏感度低、区间 $29–43K；新车保住知名度
A88: Crash | B88: $27,000 / 100 / 40 | C88: Test Market | D88: $28K +$8M；$26K 份额 4.2% → 4.5%、贡献不变 | E88: 维持
A89: Chow（Y6） | B89: — | C89: Concept Test | D89: 3S $32K 57.0%、$34K 55.4%、$36K 53.6%、$38K 51.3%；4S $36K 56.4%；3U $36K 1.1% | E89: 每个买家的贡献 $38K 最高；继续做
A90: 三情景 | B90: — | C90: startup-financial-modeling | D90: 10/28 加营销 +$460M 后（平移 −$299M，没算多卖的车）：乐观约 $20.7B；基准 $18,251M；保守 90% 约 $15.8B（现金约 $16.9B）；很差 80% 约 $13.4B（现金约 $9.4B）。10/27 版：乐观约 $21.0B；基准 $18,550M；保守 90% 约 $16.1B（现金约 $17.2B）；很差 80% 约 $13.7B（现金约 $9.7B）。加产能、分红之前：$20.6B / $18,328M / $15.9B / $13.5B | E90: 都赚钱，现金都为正；不用借钱

Sheet Y5补充测试
A1: Year 5 补充测试（10/6）：练习轮不再推进，只用 Concept Test / Test Market 测
A2: 是测试工具的预测，不是真实结果。单车毛利 = 售价 × 0.9 − Base Cost（按 10% 经销商折扣粗算，是推断）。
A4: 新车概念 | B4: 目标市场（规模） | C4: 测试价格 | D4: Likely to buy | E4: Base Cost | F4: 单车毛利（推断） | G4: 开发费 / 时间 | H4: 结论
A5: 高端 Minivan 63/200/I4 | B5: 4M（20 万辆） | C5: 38000 | D5: 0.67 | E5: 24854 | F5: =C5*0.9-E5 -> 9346 | G5: $1,469M / 3 年 | H5: ✅ 单车利润最高
A6: 豪华车 65/250/S7 Q6 | B6: 5L（31 万辆，不敏感） | C6: 45000 | D6: 0.751 | E6: 33337 | F6: =C6*0.9-E6 -> 7163 | G6: $1,633M / 3 年 | H6: ✅ 高价、不敏感
A7: 跑车 39/200/S6 | B7: 3S（51 万辆） | C7: 31000 | D7: 0.755 | E7: 22360 | F7: =C7*0.9-E7 -> 5540 | G7: $1,199M / 3 年 | H7: 可以考虑
A8: 大卡车 90/275/Q5 | B8: 1T（111 万辆，很敏感） | C8: 24000 | D8: 0.382 | E8: 19658 | F8: =C8*0.9-E8 -> 1942 | G8: $1,408M / 2 年 | H8: 利润薄；尺寸要到 93–95
A9: AEV 41/160/S7 | B9: 5A（31 万辆） | C9: 30000 | D9: 0.896 | E9: 25304 | F9: =C9*0.9-E9 -> 1696 | G9: $1,363M / 3 年 | H9: ❌ 买家多但利润薄
A10: Minivan 77/180/Sf5 Q5 | B10: 2M（41 万辆） | C10: 27000 | D10: 0.72 | E10: 24279 | F10: =C10*0.9-E10 -> 21 | G10: $1,768M / 3 年 | H10: ❌ 几乎不赚钱
A11: 小 Utility 52/180/S6 | B11: 3U（88 万辆） | C11: 22000 | D11: 0.795 | E11: 22140 | F11: =C11*0.9-E11 -> -2340 | G11: $980M / 2 年 | H11: ❌ 这个价位会亏
A12: Cameo major 24/125（2E） | B12: 2E | C12: 15000 | D12: 0.434 | E12: — | F12: — | G12: — | H12: ✅ 15.7% → 43.4%
A13: Cameo major 24/125（1E） | B13: 1E | C13: 13000 | D13: 0.108 | E13: — | F13: — | G13: — | H13: 放弃 1E
A15: 价格上限测试（Test Market） | B15: 原价 → 测试价 | C15: 份额变化 | D15: 贡献变化（$M） | H15: 结论
A16: Canyon | B16: $34,000 → $37,400 | C16: 7.2% → 7.2% | D16: 2543 | H16: ✅ 提价 10% 份额不变
A17: Cafav | B17: $21,500 → $23,600 | C17: 7.8% → 7.8% | D17: 1709 | H17: ✅
A18: Crash | B18: $23,300 → $25,600 | C18: 4.5% → 4.4% | D18: 1063 | H18: ✅
A19: Cameo | B19: $14,000 → $15,400 | C19: 3.2% → 3.2% | D19: 462 | H19: ✅
A20: Cafav 营销加倍 | B20: 160/100 → 300/150 | C20: 7.8% → 7.9% | D20: -190 | H20: ❌ 供不应求时多花营销是浪费
A22: Pro-Forma 推算：超产多少（产能 2,200K） | B22: 产量（千辆） | C22: 超产能费（$M） | D22: 净利（$M） | E22: 比上一档多赚（$M） | H22: 说明
A23: A0 产量 = 产能 | B23: 2200 | C23: 0 | D23: 8753 | H23: 按提价后的价格，并假设全部卖光
A24: A1 超产 10% | B24: 2420 | C24: 487 | D24: 9582 | E24: =D24-D23 -> 829 | H24: 每多超 1 辆约 $2,200
A25: A2 超产 20% | B25: 2640 | C25: 1100 | D25: 10329 | E25: =D25-D24 -> 747 | H25: 每多超 1 辆约 $2,800
A26: A3 超产 30% | B26: 2860 | C26: 1863 | D26: 10978 | E26: =D26-D25 -> 649 | H26: 每多超 1 辆约 $3,500
A28: Pro-Forma 推算：扩产和出钱方式（产量 110%） | B28: 做法 | C28: 今年净利（$M） | D28: 期末现金（$M） | H28: 说明
A29: B1 | B29: 扩产 +500K，用现金 | C29: 9582 | D29: 19245 | H29: 花 $3,568M（每 1K 辆约 $714K），今年净利不变
A30: B2 | B30: 扩产 +1,000K，用现金 | C30: 9582 | D30: 15740 | H30: 花 $7,073M
A31: B3 | B31: 扩产 +1,000K，增发 $5B | C31: 9582 | D31: 20740 | H31: 股数 676M → 732M，净利不变
A32: B4 | B32: 扩产 +1,000K，发债 $5B | C32: 9435 | D32: 20594 | H32: 当年利息 $225M，净利 −$147M
A33: B5 | B33: 扩产 +1,000K，买 $10B 的 CD | C33: 9777 | D33: 5935 | H33: 利息收入 $300M；CD 一次最多 $10,000M
A34: B6 | B34: 扩产 +1,000K，分红 $3B | C34: 9582 | D34: 12740 | H34: 分红不影响净利；对股价的影响看不出来

Sheet 正式比赛变数记录
A1: 正式比赛变数记录：和练习轮不一样的地方（每一期开局和出结果后都要补）
A2: 🆕 新发现，已经照着调整了 ⚠️ 和练习轮不一样，要盯着 ⏳ 还没结果 ✔️ 和练习轮一样，练习轮的结论可以继续用。和 md 第 0d 节同步。
A4: 日期 | B4: 期 | C4: 项目 | D4: 练习轮 | E4: 正式比赛 | F4: 怎么应对 | G4: 状态
A5: 10/11 | B5: D1 | C5: 截止时间 | D5: Decision 1 原定 10/12 | E5: 改成 10/14 晚 11:59（D2–D6 不变） | F5: 10/14 前再看一遍 Decision Log | G5: 🆕
A6: 10/11 | B6: D1 | C6: 开局数据 | D6: Cafav 703K / Cameo 304K / Crash 444K，产能 1,000K，短贷 $6,660M | E6: 完全一样 | F6: 练习轮的开局分析可以直接用 | G6: ✔️
A7: 10/11 | B7: D1 | C7: Start 的价格 | D7: 记录里写的 Y1 价格 $20,750 / $11,850 / $20,900 | E7: Start 价是 $20,350 / $11,492 / $20,498；练习轮记的是我们当年提价后的价格 | F7: 以后 Test Market 的 baseline 以系统显示的为准 | G7: 🆕（更正记录）
A8: 10/11 | B8: D1 | C8: 新建研发中心 | D8: 计划第 1 年建第 3、第 4 个 | E8: 系统每年只能建 1 个 | F8: Y2 只能放 Crash 或 Cameo 其中一个 major；第 4 个 Y2 再建 | G8: 🆕
A9: 10/11 | B9: D1 | C9: 细分市场偏好 | D9: 3T 尺寸偏好 57–77（练习轮 Y3 的数据） | E9: 现在是 54–74，偏好每年都在漂移 | F9: major 瞄准“上市那年”的中间值，每年重新看 Microsegment | G9: 🆕
A10: 10/11 | B10: D1 | C10: 超产能费 | D10: 练习轮 Pro-Forma：超 10% 约 $2,200 / 辆 | E10: 1,100K 时 $221M（约 $2,200 / 辆），1,200K 时 $498M | F10: 曲线一样，练习轮的结论能用 | G10: ✔️
A11: 10/11 | B11: D1 | C11: 营销的效果 | D11: 练习 Y5 测试：缺货时广告加倍反而 −$190M | E11: Y1 Test Market：Cafav 提价 10% 时广告加倍，份额 4.5% → 5.3%，贡献最高 | F11: 这一年按测试加倍了广告；出结果后看实际份额 | G11: ⚠️⏳
A12: 10/11 | B12: D1 | C12: Canyon 的 Concept Test | D12: 练习 Y3：64 / 200 HP 在 $31K 是 65.8%，HP 被评 sluggish | E12: 66 / 245 HP 在 $31K 是 81.6%，$35K 是 80.5% | F12: HP 定 245；价格还是不敏感 | G12: ✔️（更好）
A13: 10/11 | B13: D1 | C13: Cafav 新版的 Concept Test | D13: 练习 Y3：38 尺寸 $21,500 → 14.2%，$23,000 → 3.7% | E13: 38 / Sf4 / Q3：$20,500 → 20.6%，$21,500 → 12.2%，$22,500 → 9.7% | F13: 断崖还在 $21–22K 附近，Y2 定价要小心 | G13: ✔️
A14: 10/16 | B14: Y1 结果 | C14: 对手动向 | D14: 练习轮各家第 1 年动作不大，F 在 Y3 才宣布做 Utility | E14: 对手都练过了：A、B、D、E、F 都建了第 3 个研发中心（只有 G 没建）；A 升级 Alfa（2F 第一）、D 升级 Defy 和 Dusty（Dusty $24,000，5U 第一）、G 升级 Gas 和 Gone（Gone 3T 第一）；F 研发费最高（$1,965M） | F14: 还没有一家有 Utility 车；盯住 F [推断] | G14: ⚠️
A15: 10/16 | B15: Y1 结果 | C15: 全行业实际销量 | D15: Y2 10,078K、Y3 10,339K | E15: 8,961K（−13.1%），比预测少 15%，比我们假设的 10,100K 少 11% | F15: 按“全行业产能 × 约 110%”估；Y2 全行业产能约 9,400K [推断] | G15: ⚠️
... A69: 10/28 | B69: D5 | C69: 测试次数上限 | D69: 练习轮没用满过 | E69: Test Market 和 Concept Test 每年各最多 10 次；D5 的 Test Market 10/27 就用完了，10/28 加营销时没法再测 | F69: 改营销或价格前先看还剩几次；没测的预算在 Rationale 里写明 | G69: 🆕
A71: 每一期出结果后要补的检查
A72: 1 | B72: 我们每辆车的实际份额 vs Test Market 预测（练习轮误差 ≤ 0.4 个百分点；正式 Y1 实际高 0.5–0.8 点）
A73: 2 | B73: 全行业实际销量 vs 预测（练习轮只有预测的 76–85%；正式 Y1 只有 85%）
A74: 3 | B74: 对手：谁提价、谁出了新车（尤其是 Utility / 5U、Minivan / 4M）、谁扩产、谁增发
A75: 4 | B75: 系统有没有出 Special Decisions、规则或日程有没有变
A76: 5 | B76: Pro-Forma 的净利 vs 实际净利（练习轮每年高估约 $700M；正式 Y1 低估了 $81M）

Sheet 更新记录
A1: 这份表的更新记录
A2: 文件名 10/11 起改成“StratSim_练习与正式比赛对照表.xlsx”（原来叫“StratSim_前三年对照表.xlsx”）。每次改这份表都在最下面加一行。
A4: 日期 | B4: 改了什么 | C4: 涉及的页
A5: 10/6 及以前 | B5: 建表并记录练习轮 Y1–Y4 的决策和结果、结论总表、操作流程、Skill 和测试工具、Y5 补充测试、正式比赛打法（当时的文件名是“前三年对照表”） | C5: 前 7 页
A6: 10/11 | B6: 正式 Decision 1 保存后补记录：正式比赛打法加 D 列（实际怎么做的）；每年做了什么加 G 列（正式 Y1）；每年的结果加 H 列（正式 Y1 的 Pro-Forma）；结论总表加第 49–55 行；Skill和测试工具补了正式 Y1 的发现；操作流程第 4 步加“每年只能新建 1 个中心” | C6: 正式比赛打法、每年做了什么、每年的结果、结论总表、Skill和测试工具、操作流程
A7: 10/11 | B7: 新增“正式比赛变数记录”页（12 条）；Skill和测试工具加“每一期有没有跑 skill”表和“正式 Y1 pricing 复查”表（带公式）；操作流程第 14 步改成要记 skill 复查和变数 | C7: 正式比赛变数记录、Skill和测试工具、操作流程
A8: 10/11 | B8: 文件改名：StratSim_前三年对照表.xlsx → StratSim_练习与正式比赛对照表.xlsx（内容早就不止前三年）；新增这一页“更新记录”；“每年做了什么”的标题改成“练习 Y1–Y4 + 正式比赛” | C8: 全部
A9: 10/16 | B9: 正式 Year 1 结果出来后补记录：新增“正式Y1复盘”页（预测 vs 实际、每个数据涨跌的原因、七家对比、为什么 G 第一、问题和教训、年度财务目标）；“每年的结果”H 列改成正式 Y1 实际值，新增 I 列放 Pro-Forma；“正式比赛变数记录”填上结果并新增 4 条；“结论总表”更新第 52–53 行，新增第 56–59 行 | C9: 正式Y1复盘、每年的结果、正式比赛变数记录、结论总表
A10: 10/16 | B10: 正式 Decision 2 保存后补记录：“每年做了什么”加 H 列（正式 Y2）；“每年的结果”加 J 列（正式 Y2 Pro-Forma）；“正式比赛变数记录”新增 4 条（扩产上限 50%、经销商上限、利率、retooling）；“结论总表”新增第 60–65 行；“Skill和测试工具”加正式 Y2 的使用记录和 Y2 定价复查表 | C10: 每年做了什么、每年的结果、正式比赛变数记录、结论总表、Skill和测试工具
A11: 10/16 | B11: 提交前复查 Y1、Y2：发现 Cameo 的 Flex 被错误关掉（照搬 Y1 教训），已在系统里改回并重写 Rationale；“结论总表”第 64 行改成 ❌ 教训；“每年的结果”J 列更新为最终 Pro-Forma（净利 $2,663M、现金 $1,024M）；“正式比赛变数记录”的 Flex 行补上适用条件 | C11: 结论总表、每年的结果、正式比赛变数记录
A12: 10/17 | B12: 正式 Year 2 结果出来后补记录：新增“正式Y2复盘”页；“每年的结果”加 K 列（正式 Y2 实际）；“正式比赛变数记录”新增 6 条；“结论总表”把 Y2 验证过的 ⏳ 改成 ✅，新增 2 条 | C12: 正式Y2复盘、每年的结果、正式比赛变数记录、结论总表
A13: 10/17 | B13: 正式 Decision 3 保存后补记录：“每年做了什么”加 I 列（正式 Y3）；“每年的结果”加 L 列（正式 Y3 Pro-Forma）；“正式比赛变数记录”新增 4 条；“结论总表”新增 7 条；“Skill和测试工具”加 Y3 的最终组合测试表 | C13: 每年做了什么、每年的结果、正式比赛变数记录、结论总表、Skill和测试工具
A14: 10/24 | B14: 正式 Year 3 结果出来后补记录：新增“正式Y3复盘”页（预测 vs 实际、Y2 → Y3 每个数据涨跌的原因、七家对比和我们为什么第一、问题和教训、年度财务目标）；“每年的结果”加 M 列（正式 Y3 实际）；“结论总表”把 3 条 Y3 的 ⏳ 改成 ✅，新增 2 条（❌ 新车首年排产偏多、✅ 老车提价后仍缺货）；“正式比赛变数记录”新增 6 条。 | C14: 正式Y3复盘、每年的结果、结论总表、正式比赛变数记录
A15: 10/25 | B15: 正式 Decision 4 保存后补记录：“每年做了什么”加 J 列（正式 Y4），并新增“中心 5”和“Cosmo”两行（同页公式已改到新行号）；“每年的结果”加 N 列（正式 Y4 Pro-Forma）；“Skill和测试工具”加正式 Y4 的测试和复查表；“结论总表”新增 7 条 ⏳；“正式比赛变数记录”新增 7 条。 | C15: 每年做了什么、每年的结果、Skill和测试工具、结论总表、正式比赛变数记录
... A23: 10/28 | B23: 用户提出多花营销：营销 $1,753M → $2,213M（营收 2.5%）。“每年做了什么”K6、K22，“每年的结果”P5、P15，“Skill和测试工具”三情景已更新；“结论总表”和“正式比赛变数记录”各新增 1 条。 | C23: 每年做了什么、每年的结果、Skill和测试工具、结论总表、正式比赛变数记录
